[{"cn":"NOKIY_1","pi":"422550","ui":"5330923","t":1066679,"r":1066679,"q":18.41,"p":10000.0,"mot":"U","mo":0.0},{"cn":"vester0 Трейд","pi":"422550","ui":"6598074","t":76337,"r":29526,"q":25.91,"p":3999.0,"mot":"U","mo":0.0},{"cn":"Cit-Mag","pi":"422550","ui":"6605904","t":99545,"r":791,"q":25.1,"p":3700.0,"mot":"U","mo":0.0},{"cn":"николаев Инвест","pi":"422550","ui":"6073685","t":31064,"r":3221,"q":15.37,"p":3299.0,"mot":"U","mo":0.0},{"cn":"NewMax Group","pi":"422550","ui":"5665840","t":273340,"r":111639,"q":28.95,"p":5100.0,"mot":"U","mo":0.0},{"cn":"Nikser Standard","pi":"422550","ui":"5189435","t":1992048,"r":1426189,"q":27.61,"p":5699.0,"mot":"U","mo":0.0},{"cn":"PS_loki Трейд","pi":"422550","ui":"5672948","t":2152414,"r":2152413,"q":16.88,"p":6500.0,"mot":"U","mo":0.0},{"cn":"PS_loki Трейд","pi":"422550","ui":"5672947","t":601326,"r":601015,"q":15.72,"p":6500.0,"mot":"L","mo":10000.0},{"cn":"Crolla Invest","pi":"422550","ui":"5768794","t":150778,"r":150728,"q":18.05,"p":90000.0,"mot":"L","mo":20.0},{"cn":"PS_loki Трейд","pi":"422550","ui":"5775960","t":109792,"r":89688,"q":17.1,"p":16775.0,"mot":"L","mo":10000.0},{"cn":"BelKOZ inc.","pi":"422550","ui":"6489716","t":59199,"r":56986,"q":17.63,"p":4000.0,"mot":"U","mo":0.0},{"cn":"SLL Group","pi":"422550","ui":"6591545","t":123574,"r":118970,"q":27.23,"p":7300.0,"mot":"U","mo":0.0},{"cn":"Omahen International","pi":"422550","ui":"6357622","t":820,"r":820,"q":18.05,"p":500000.0,"mot":"U","mo":0.0},{"cn":"vester0 Трейд","pi":"422550","ui":"5775450","t":117603,"r":103510,"q":26.01,"p":3999.0,"mot":"U","mo":0.0},{"cn":"jz48","pi":"422550","ui":"5660206","t":66165,"r":61663,"q":19.9,"p":6898.32,"mot":"U","mo":0.0},{"cn":"trihon Инвест","pi":"422550","ui":"5989802","t":42908,"r":42906,"q":18.28,"p":5550.0,"mot":"U","mo":0.0},{"cn":"Mihalih Іnvest","pi":"422550","ui":"6685552","t":22354,"r":21851,"q":5.99,"p":3500.0,"mot":"U","mo":0.0},{"cn":"Redicson Трейд","pi":"422550","ui":"6636576","t":15274786,"r":15274784,"q":28.35,"p":8000.0,"mot":"U","mo":0.0},{"cn":"\"Korsa\" Corp.","pi":"422550","ui":"6502228","t":14285,"r":13085,"q":23.45,"p":8000.0,"mot":"U","mo":0.0},{"cn":"jz48","pi":"422550","ui":"5682991","t":584000,"r":556148,"q":16.82,"p":5145.21,"mot":"U","mo":0.0},{"cn":"jz48","pi":"422550","ui":"5682990","t":22946,"r":22944,"q":14.76,"p":4590.12,"mot":"U","mo":0.0}]