[{"cn":"Pavlei finance","pi":"423151","ui":"7166511","t":5170,"r":5070,"q":1.61,"p":3.0,"mot":"U","mo":0.0},{"cn":"Staywood Company","pi":"423151","ui":"7164120","t":3843208,"r":3821882,"q":1.53,"p":3.0,"mot":"L","mo":50000.0},{"cn":"dimamishko Инвест","pi":"423151","ui":"7154383","t":14632,"r":13571,"q":1.0,"p":2.7,"mot":"U","mo":0.0},{"cn":"dimamishko Инвест","pi":"423151","ui":"7154382","t":113955,"r":113955,"q":1.0,"p":2.9,"mot":"U","mo":0.0},{"cn":"dimamishko Инвест","pi":"423151","ui":"7154384","t":11000,"r":10300,"q":1.32,"p":2.81,"mot":"U","mo":0.0},{"cn":"Smitworld","pi":"423151","ui":"7156576","t":4960,"r":2860,"q":1.13,"p":2.0,"mot":"U","mo":0.0},{"cn":"Иванов Инвест","pi":"423151","ui":"7155228","t":37500,"r":37500,"q":1.03,"p":2.0,"mot":"U","mo":0.0},{"cn":"Kapodastr Инвест","pi":"423151","ui":"7173927","t":22161,"r":22161,"q":1.44,"p":4.0,"mot":"U","mo":0.0},{"cn":"Гафуров Финанс","pi":"423151","ui":"7218703","t":10000,"r":10000,"q":1.0,"p":23.0,"mot":"U","mo":0.0},{"cn":"Z.B.K. Finans","pi":"423151","ui":"7149651","t":9230,"r":2180,"q":1.0,"p":2.0,"mot":"U","mo":0.0},{"cn":"Гафуров Финанс","pi":"423151","ui":"7201607","t":7819,"r":7819,"q":1.0,"p":8.0,"mot":"U","mo":0.0},{"cn":"CREATIVE Трейд","pi":"423151","ui":"7143981","t":215218,"r":109717,"q":4.02,"p":8.0,"mot":"U","mo":0.0},{"cn":"Boys Toys","pi":"423151","ui":"7189315","t":100000,"r":100000,"q":2.25,"p":7.0,"mot":"U","mo":0.0},{"cn":"ILAV Incorporated","pi":"423151","ui":"7141137","t":20890,"r":20890,"q":1.0,"p":8.0,"mot":"U","mo":0.0},{"cn":"Территория жизни","pi":"423151","ui":"7148830","t":345760,"r":345760,"q":1.47,"p":5.0,"mot":"U","mo":0.0},{"cn":"Анубис-индастрит","pi":"423151","ui":"7216771","t":4620,"r":4620,"q":1.62,"p":70.0,"mot":"L","mo":4620.0},{"cn":"packham101 Limited","pi":"423151","ui":"7170518","t":37390,"r":37390,"q":1.0,"p":3.79,"mot":"U","mo":0.0},{"cn":"Finist","pi":"423151","ui":"7179380","t":111138,"r":111138,"q":1.11,"p":2.99,"mot":"U","mo":0.0},{"cn":"dog1251 Инвест","pi":"423151","ui":"7161436","t":38773,"r":28456,"q":1.08,"p":1.7,"mot":"U","mo":0.0},{"cn":"Monohrom Inc.","pi":"423151","ui":"7194570","t":33160,"r":9867,"q":1.9,"p":1.65,"mot":"U","mo":0.0},{"cn":"Dron.Corp","pi":"423151","ui":"7141634","t":178935,"r":122685,"q":3.98,"p":7.5,"mot":"L","mo":30000.0}]