[{"cn":"АО «BLESK»","pi":"422380","ui":"5922201","t":925005,"r":922695,"q":16.95,"p":30000.0,"mot":"U","mo":0.0},{"cn":"Салун Финанс","pi":"422380","ui":"6207634","t":2086,"r":2086,"q":6.92,"p":55000.0,"mot":"U","mo":0.0},{"cn":"pavel32024 и сыновья","pi":"422380","ui":"5137598","t":4974,"r":4962,"q":25.0,"p":220000.0,"mot":"L","mo":10.0},{"cn":"QXM","pi":"422380","ui":"7210102","t":6896,"r":6895,"q":1.5,"p":33000.0,"mot":"U","mo":0.0},{"cn":"Signal","pi":"422380","ui":"7187338","t":422113,"r":417422,"q":12.83,"p":24000.0,"mot":"U","mo":0.0},{"cn":"SimoneNatali Rulezzz!","pi":"422380","ui":"5598238","t":36682,"r":36071,"q":11.34,"p":30500.0,"mot":"U","mo":0.0}]