[{"ci":"3054","ri":"3055","ti":"3056","v":25908249,"p":45.34,"sc":10,"cc":10,"mdi":2.0,"pbs":{},"rbs":{"Оператор мобильной связи":{}},"cbs":{"Оператор мобильной связи":{"lpr":0.0,"lq":0.0,"spr":0.0,"sq":0.0}},"wi":37.55,"itr":31.0,"ar":8815.0},{"ci":"3054","ri":"3055","ti":"3057","v":811190,"p":72.42,"sc":6,"cc":6,"mdi":1.66,"pbs":{},"rbs":{"Оператор мобильной связи":{}},"cbs":{"Оператор мобильной связи":{"lpr":0.0,"lq":0.0,"spr":0.0,"sq":0.0}},"wi":8.4,"itr":31.0,"ar":1959.0},{"ci":"3054","ri":"3055","ti":"422527","v":162718,"p":125.33,"sc":2,"cc":2,"mdi":1.96,"pbs":{},"rbs":{"Оператор мобильной связи":{}},"cbs":{"Оператор мобильной связи":{"lpr":0.0,"lq":0.0,"spr":0.0,"sq":0.0}},"wi":12.05,"itr":31.0,"ar":3224.81},{"ci":"3054","ri":"3055","ti":"3058","v":300537,"p":113.41,"sc":2,"cc":2,"mdi":1.15,"pbs":{},"rbs":{"Оператор мобильной связи":{}},"cbs":{"Оператор мобильной связи":{"lpr":0.0,"lq":0.0,"spr":0.0,"sq":0.0}},"wi":11.89,"itr":31.0,"ar":2370.45},{"ci":"303829","ri":"303830","ti":"423575","v":93122,"p":242.25,"sc":4,"cc":4,"mdi":1.95,"pbs":{},"rbs":{"Оператор мобильной связи":{}},"cbs":{"Оператор мобильной связи":{"lpr":0.0,"lq":0.0,"spr":0.0,"sq":0.0}},"wi":29.37,"itr":17.0,"ar":4356.0},{"ci":"303829","ri":"303830","ti":"303833","v":766673,"p":122.11,"sc":8,"cc":7,"mdi":2.13,"pbs":{},"rbs":{"Оператор мобильной связи":{}},"cbs":{"Оператор мобильной связи":{"lpr":0.0,"lq":0.0,"spr":0.0,"sq":0.0}},"wi":23.35,"itr":17.0,"ar":3900.56},{"ci":"303829","ri":"303830","ti":"303832","v":1683520,"p":246.56,"sc":5,"cc":5,"mdi":2.13,"pbs":{},"rbs":{"Оператор мобильной связи":{}},"cbs":{"Оператор мобильной связи":{"lpr":0.0,"lq":0.0,"spr":0.0,"sq":0.0}},"wi":24.66,"itr":17.0,"ar":21559.0},{"ci":"303829","ri":"303830","ti":"303831","v":42285225,"p":78.12,"sc":13,"cc":12,"mdi":3.89,"pbs":{},"rbs":{"Оператор мобильной связи":{}},"cbs":{"Оператор мобильной связи":{"lpr":0.0,"lq":0.0,"spr":0.0,"sq":0.0}},"wi":63.62,"itr":17.0,"ar":11406.92},{"ci":"303253","ri":"303254","ti":"303257","v":368000,"p":1023.36,"sc":6,"cc":6,"mdi":2.76,"pbs":{},"rbs":{"Оператор мобильной связи":{}},"cbs":{"Оператор мобильной связи":{"lpr":0.0,"lq":0.0,"spr":0.0,"sq":0.0}},"wi":42.51,"itr":16.0,"ar":26887.0},{"ci":"303253","ri":"303254","ti":"303256","v":521214,"p":1565.36,"sc":7,"cc":7,"mdi":3.4,"pbs":{},"rbs":{"Оператор мобильной связи":{}},"cbs":{"Оператор мобильной связи":{"lpr":0.0,"lq":0.0,"spr":0.0,"sq":0.0}},"wi":66.92,"itr":16.0,"ar":16884.79},{"ci":"303253","ri":"303254","ti":"423033","v":92779,"p":469.63,"sc":4,"cc":4,"mdi":1.83,"pbs":{},"rbs":{"Оператор мобильной связи":{}},"cbs":{"Оператор мобильной связи":{"lpr":0.0,"lq":0.0,"spr":0.0,"sq":0.0}},"wi":29.44,"itr":16.0,"ar":6812.62},{"ci":"303253","ri":"303254","ti":"423021","v":69285,"p":145.13,"sc":2,"cc":2,"mdi":1.11,"pbs":{},"rbs":{"Оператор мобильной связи":{}},"cbs":{"Оператор мобильной связи":{"lpr":0.0,"lq":0.0,"spr":0.0,"sq":0.0}},"wi":15.58,"itr":16.0,"ar":4335.21},{"ci":"303253","ri":"303254","ti":"423022","v":110184,"p":500.05,"sc":3,"cc":3,"mdi":2.14,"pbs":{},"rbs":{"Оператор мобильной связи":{}},"cbs":{"Оператор мобильной связи":{"lpr":0.0,"lq":0.0,"spr":0.0,"sq":0.0}},"wi":25.07,"itr":16.0,"ar":5771.04},{"ci":"303253","ri":"303254","ti":"422076","v":21508,"p":803.92,"sc":2,"cc":2,"mdi":1.5,"pbs":{},"rbs":{"Оператор мобильной связи":{}},"cbs":{"Оператор мобильной связи":{"lpr":0.0,"lq":0.0,"spr":0.0,"sq":0.0}},"wi":16.88,"itr":16.0,"ar":3773.42},{"ci":"303253","ri":"303254","ti":"303261","v":239346,"p":799.08,"sc":4,"cc":4,"mdi":2.6,"pbs":{},"rbs":{"Оператор мобильной связи":{}},"cbs":{"Оператор мобильной связи":{"lpr":0.0,"lq":0.0,"spr":0.0,"sq":0.0}},"wi":47.26,"itr":16.0,"ar":13576.67},{"ci":"303253","ri":"303254","ti":"303258","v":398525,"p":1327.86,"sc":6,"cc":6,"mdi":2.66,"pbs":{},"rbs":{"Оператор мобильной связи":{}},"cbs":{"Оператор мобильной связи":{"lpr":0.0,"lq":0.0,"spr":0.0,"sq":0.0}},"wi":40.44,"itr":16.0,"ar":6505.96},{"ci":"303253","ri":"303254","ti":"303260","v":261423,"p":838.02,"sc":3,"cc":3,"mdi":2.44,"pbs":{},"rbs":{"Оператор мобильной связи":{}},"cbs":{"Оператор мобильной связи":{"lpr":0.0,"lq":0.0,"spr":0.0,"sq":0.0}},"wi":39.5,"itr":16.0,"ar":9605.97},{"ci":"303253","ri":"303254","ti":"422496","v":135589,"p":500.05,"sc":3,"cc":3,"mdi":2.05,"pbs":{},"rbs":{"Оператор мобильной связи":{}},"cbs":{"Оператор мобильной связи":{"lpr":0.0,"lq":0.0,"spr":0.0,"sq":0.0}},"wi":27.24,"itr":16.0,"ar":7640.74},{"ci":"303253","ri":"303254","ti":"423574","v":13558,"p":261.75,"sc":3,"cc":3,"mdi":1.1,"pbs":{},"rbs":{"Оператор мобильной связи":{}},"cbs":{"Оператор мобильной связи":{"lpr":0.0,"lq":0.0,"spr":0.0,"sq":0.0}},"wi":15.1,"itr":16.0,"ar":3602.65},{"ci":"303253","ri":"303254","ti":"303255","v":38923159,"p":142.9,"sc":16,"cc":16,"mdi":4.06,"pbs":{},"rbs":{"Оператор мобильной связи":{}},"cbs":{"Оператор мобильной связи":{"lpr":0.0,"lq":0.0,"spr":0.0,"sq":0.0}},"wi":66.62,"itr":16.0,"ar":43803.26},{"ci":"303253","ri":"303254","ti":"303259","v":1495831,"p":188.85,"sc":5,"cc":5,"mdi":2.66,"pbs":{},"rbs":{"Оператор мобильной связи":{}},"cbs":{"Оператор мобильной связи":{"lpr":0.0,"lq":0.0,"spr":0.0,"sq":0.0}},"wi":41.35,"itr":16.0,"ar":15095.37},{"ci":"423837","ri":"423840","ti":"423854","v":1022547,"p":391.32,"sc":8,"cc":8,"mdi":1.18,"pbs":{},"rbs":{"Оператор мобильной связи":{}},"cbs":{"Оператор мобильной связи":{"lpr":0.0,"lq":0.0,"spr":0.0,"sq":0.0}},"wi":31.23,"itr":22.0,"ar":6407.14},{"ci":"423837","ri":"423840","ti":"423849","v":853587,"p":136.7,"sc":12,"cc":11,"mdi":0.6,"pbs":{},"rbs":{"Оператор мобильной связи":{}},"cbs":{"Оператор мобильной связи":{"lpr":0.0,"lq":0.0,"spr":0.0,"sq":0.0}},"wi":16.4,"itr":22.0,"ar":3015.82},{"ci":"423837","ri":"423839","ti":"423859","v":184280,"p":286.56,"sc":7,"cc":7,"mdi":0.49,"pbs":{},"rbs":{"Оператор мобильной связи":{}},"cbs":{"Оператор мобильной связи":{"lpr":0.0,"lq":0.0,"spr":0.0,"sq":0.0}},"wi":16.03,"itr":22.0,"ar":2308.26},{"ci":"423837","ri":"423839","ti":"423851","v":334274,"p":367.2,"sc":6,"cc":6,"mdi":0.72,"pbs":{},"rbs":{"Оператор мобильной связи":{}},"cbs":{"Оператор мобильной связи":{"lpr":0.0,"lq":0.0,"spr":0.0,"sq":0.0}},"wi":17.06,"itr":22.0,"ar":4075.0},{"ci":"423837","ri":"423839","ti":"423845","v":7737028,"p":112.0,"sc":16,"cc":16,"mdi":1.2,"pbs":{},"rbs":{"Оператор мобильной связи":{}},"cbs":{"Оператор мобильной связи":{"lpr":0.0,"lq":0.0,"spr":0.0,"sq":0.0}},"wi":35.46,"itr":22.0,"ar":6998.63},{"ci":"423837","ri":"423839","ti":"423858","v":202480,"p":152.86,"sc":6,"cc":6,"mdi":0.27,"pbs":{},"rbs":{"Оператор мобильной связи":{}},"cbs":{"Оператор мобильной связи":{"lpr":0.0,"lq":0.0,"spr":0.0,"sq":0.0}},"wi":17.2,"itr":22.0,"ar":2664.85},{"ci":"423837","ri":"423839","ti":"423847","v":9051906,"p":109.52,"sc":8,"cc":8,"mdi":1.56,"pbs":{},"rbs":{"Оператор мобильной связи":{}},"cbs":{"Оператор мобильной связи":{"lpr":0.0,"lq":0.0,"spr":0.0,"sq":0.0}},"wi":33.11,"itr":22.0,"ar":7671.2},{"ci":"423837","ri":"423838","ti":"423846","v":48807926,"p":102.62,"sc":10,"cc":10,"mdi":3.33,"pbs":{},"rbs":{"Оператор мобильной связи":{}},"cbs":{"Оператор мобильной связи":{"lpr":0.0,"lq":0.0,"spr":0.0,"sq":0.0}},"wi":82.96,"itr":22.0,"ar":17979.0},{"ci":"423837","ri":"423838","ti":"423853","v":364167,"p":265.82,"sc":6,"cc":6,"mdi":0.64,"pbs":{},"rbs":{"Оператор мобильной связи":{}},"cbs":{"Оператор мобильной связи":{"lpr":0.0,"lq":0.0,"spr":0.0,"sq":0.0}},"wi":15.76,"itr":22.0,"ar":2695.0},{"ci":"423837","ri":"423841","ti":"423848","v":3901884,"p":294.66,"sc":11,"cc":11,"mdi":1.85,"pbs":{},"rbs":{"Оператор мобильной связи":{}},"cbs":{"Оператор мобильной связи":{"lpr":0.0,"lq":0.0,"spr":0.0,"sq":0.0}},"wi":35.91,"itr":34.0,"ar":7203.0},{"ci":"423837","ri":"423841","ti":"423855","v":211361,"p":518.82,"sc":4,"cc":3,"mdi":0.74,"pbs":{},"rbs":{"Оператор мобильной связи":{}},"cbs":{"Оператор мобильной связи":{"lpr":0.0,"lq":0.0,"spr":0.0,"sq":0.0}},"wi":17.07,"itr":34.0,"ar":2609.0},{"ci":"423837","ri":"423841","ti":"423856","v":150707,"p":593.74,"sc":2,"cc":2,"mdi":0.69,"pbs":{},"rbs":{"Оператор мобильной связи":{}},"cbs":{"Оператор мобильной связи":{"lpr":0.0,"lq":0.0,"spr":0.0,"sq":0.0}},"wi":16.45,"itr":34.0,"ar":2257.36},{"ci":"423837","ri":"423841","ti":"423844","v":13551869,"p":310.64,"sc":22,"cc":22,"mdi":1.59,"pbs":{},"rbs":{"Оператор мобильной связи":{}},"cbs":{"Оператор мобильной связи":{"lpr":0.0,"lq":0.0,"spr":0.0,"sq":0.0}},"wi":57.22,"itr":34.0,"ar":11519.0},{"ci":"423837","ri":"423841","ti":"423857","v":169906,"p":533.18,"sc":4,"cc":4,"mdi":0.77,"pbs":{},"rbs":{"Оператор мобильной связи":{}},"cbs":{"Оператор мобильной связи":{"lpr":0.0,"lq":0.0,"spr":0.0,"sq":0.0}},"wi":16.5,"itr":34.0,"ar":2151.49},{"ci":"423837","ri":"423841","ti":"423843","v":40592504,"p":214.54,"sc":29,"cc":26,"mdi":1.87,"pbs":{},"rbs":{"Оператор мобильной связи":{}},"cbs":{"Оператор мобильной связи":{"lpr":0.0,"lq":0.0,"spr":0.0,"sq":0.0}},"wi":52.01,"itr":34.0,"ar":10164.87},{"ci":"423837","ri":"423842","ti":"423850","v":5234247,"p":148.18,"sc":7,"cc":7,"mdi":1.56,"pbs":{},"rbs":{"Оператор мобильной связи":{}},"cbs":{"Оператор мобильной связи":{"lpr":0.0,"lq":0.0,"spr":0.0,"sq":0.0}},"wi":38.51,"itr":23.0,"ar":8038.0},{"ci":"423837","ri":"423842","ti":"423852","v":69414,"p":1376.22,"sc":6,"cc":6,"mdi":0.66,"pbs":{},"rbs":{"Оператор мобильной связи":{}},"cbs":{"Оператор мобильной связи":{"lpr":0.0,"lq":0.0,"spr":0.0,"sq":0.0}},"wi":18.53,"itr":23.0,"ar":3939.0},{"ci":"15904","ri":"15916","ti":"15936","v":77868510,"p":358.12,"sc":31,"cc":29,"mdi":7.81,"pbs":{},"rbs":{"Оператор мобильной связи":{}},"cbs":{"Оператор мобильной связи":{"lpr":0.0,"lq":0.0,"spr":0.0,"sq":0.0}},"wi":117.9,"itr":41.0,"ar":28780.0},{"ci":"15904","ri":"15916","ti":"422981","v":3314865,"p":484.93,"sc":8,"cc":8,"mdi":3.94,"pbs":{},"rbs":{"Оператор мобильной связи":{}},"cbs":{"Оператор мобильной связи":{"lpr":0.0,"lq":0.0,"spr":0.0,"sq":0.0}},"wi":105.73,"itr":41.0,"ar":19711.32},{"ci":"15904","ri":"15916","ti":"352886","v":8796317,"p":156.67,"sc":6,"cc":6,"mdi":3.81,"pbs":{},"rbs":{"Оператор мобильной связи":{}},"cbs":{"Оператор мобильной связи":{"lpr":0.0,"lq":0.0,"spr":0.0,"sq":0.0}},"wi":93.23,"itr":41.0,"ar":35525.0},{"ci":"15904","ri":"15916","ti":"422514","v":675469,"p":677.14,"sc":4,"cc":4,"mdi":3.76,"pbs":{},"rbs":{"Оператор мобильной связи":{}},"cbs":{"Оператор мобильной связи":{"lpr":0.0,"lq":0.0,"spr":0.0,"sq":0.0}},"wi":75.97,"itr":41.0,"ar":14860.0},{"ci":"15904","ri":"15916","ti":"15943","v":1802985,"p":812.82,"sc":6,"cc":6,"mdi":3.62,"pbs":{},"rbs":{"Оператор мобильной связи":{}},"cbs":{"Оператор мобильной связи":{"lpr":0.0,"lq":0.0,"spr":0.0,"sq":0.0}},"wi":80.74,"itr":41.0,"ar":16852.84},{"ci":"15904","ri":"15916","ti":"375138","v":1115676,"p":624.01,"sc":3,"cc":3,"mdi":2.32,"pbs":{},"rbs":{"Оператор мобильной связи":{}},"cbs":{"Оператор мобильной связи":{"lpr":0.0,"lq":0.0,"spr":0.0,"sq":0.0}},"wi":66.16,"itr":41.0,"ar":23241.8},{"ci":"15904","ri":"15916","ti":"373539","v":2569401,"p":835.16,"sc":6,"cc":6,"mdi":4.87,"pbs":{},"rbs":{"Оператор мобильной связи":{}},"cbs":{"Оператор мобильной связи":{"lpr":0.0,"lq":0.0,"spr":0.0,"sq":0.0}},"wi":112.04,"itr":41.0,"ar":24037.0},{"ci":"15904","ri":"15916","ti":"15938","v":18850635,"p":202.59,"sc":9,"cc":9,"mdi":5.6,"pbs":{},"rbs":{"Оператор мобильной связи":{}},"cbs":{"Оператор мобильной связи":{"lpr":0.0,"lq":0.0,"spr":0.0,"sq":0.0}},"wi":105.35,"itr":41.0,"ar":23399.0},{"ci":"15904","ri":"15916","ti":"15935","v":300599182,"p":311.66,"sc":82,"cc":71,"mdi":9.64,"pbs":{},"rbs":{"Оператор мобильной связи":{}},"cbs":{"Оператор мобильной связи":{"lpr":0.0,"lq":0.0,"spr":0.0,"sq":0.0}},"wi":91.03,"itr":41.0,"ar":55531.82},{"ci":"15904","ri":"15916","ti":"422941","v":113690,"p":691.99,"sc":3,"cc":3,"mdi":2.5,"pbs":{},"rbs":{"Оператор мобильной связи":{}},"cbs":{"Оператор мобильной связи":{"lpr":0.0,"lq":0.0,"spr":0.0,"sq":0.0}},"wi":52.43,"itr":41.0,"ar":13204.8},{"ci":"15904","ri":"15916","ti":"15941","v":20500389,"p":399.55,"sc":11,"cc":11,"mdi":5.45,"pbs":{},"rbs":{"Оператор мобильной связи":{}},"cbs":{"Оператор мобильной связи":{"lpr":0.0,"lq":0.0,"spr":0.0,"sq":0.0}},"wi":88.06,"itr":41.0,"ar":16263.45},{"ci":"15904","ri":"15916","ti":"423565","v":774834,"p":1018.73,"sc":2,"cc":2,"mdi":3.37,"pbs":{},"rbs":{"Оператор мобильной связи":{}},"cbs":{"Оператор мобильной связи":{"lpr":0.0,"lq":0.0,"spr":0.0,"sq":0.0}},"wi":93.84,"itr":41.0,"ar":18996.08},{"ci":"15904","ri":"15916","ti":"423547","v":302535,"p":775.36,"sc":2,"cc":2,"mdi":2.04,"pbs":{},"rbs":{"Оператор мобильной связи":{}},"cbs":{"Оператор мобильной связи":{"lpr":0.0,"lq":0.0,"spr":0.0,"sq":0.0}},"wi":62.61,"itr":41.0,"ar":10418.63},{"ci":"15904","ri":"15916","ti":"348029","v":22625735,"p":234.77,"sc":12,"cc":12,"mdi":5.11,"pbs":{},"rbs":{"Оператор мобильной связи":{}},"cbs":{"Оператор мобильной связи":{"lpr":0.0,"lq":0.0,"spr":0.0,"sq":0.0}},"wi":128.78,"itr":41.0,"ar":70448.7},{"ci":"375142","ri":"375143","ti":"375147","v":15671064,"p":125.52,"sc":15,"cc":11,"mdi":3.48,"pbs":{},"rbs":{"Оператор мобильной связи":{}},"cbs":{"Оператор мобильной связи":{"lpr":0.0,"lq":0.0,"spr":0.0,"sq":0.0}},"wi":52.19,"itr":29.0,"ar":19228.17},{"ci":"375142","ri":"375143","ti":"375151","v":2992494,"p":135.87,"sc":14,"cc":11,"mdi":2.58,"pbs":{},"rbs":{"Оператор мобильной связи":{}},"cbs":{"Оператор мобильной связи":{"lpr":0.0,"lq":0.0,"spr":0.0,"sq":0.0}},"wi":32.55,"itr":29.0,"ar":12016.15},{"ci":"375142","ri":"375143","ti":"375146","v":22064439,"p":133.7,"sc":10,"cc":10,"mdi":3.14,"pbs":{},"rbs":{"Оператор мобильной связи":{}},"cbs":{"Оператор мобильной связи":{"lpr":0.0,"lq":0.0,"spr":0.0,"sq":0.0}},"wi":65.25,"itr":29.0,"ar":22786.47},{"ci":"375142","ri":"375143","ti":"375144","v":54928533,"p":179.58,"sc":21,"cc":19,"mdi":4.07,"pbs":{},"rbs":{"Оператор мобильной связи":{}},"cbs":{"Оператор мобильной связи":{"lpr":0.0,"lq":0.0,"spr":0.0,"sq":0.0}},"wi":82.91,"itr":29.0,"ar":17049.9},{"ci":"375142","ri":"375143","ti":"375149","v":2523004,"p":138.95,"sc":4,"cc":4,"mdi":2.0,"pbs":{},"rbs":{"Оператор мобильной связи":{}},"cbs":{"Оператор мобильной связи":{"lpr":0.0,"lq":0.0,"spr":0.0,"sq":0.0}},"wi":37.76,"itr":29.0,"ar":13178.52},{"ci":"375142","ri":"375143","ti":"375145","v":20965210,"p":222.47,"sc":12,"cc":11,"mdi":3.62,"pbs":{},"rbs":{"Оператор мобильной связи":{}},"cbs":{"Оператор мобильной связи":{"lpr":0.0,"lq":0.0,"spr":0.0,"sq":0.0}},"wi":74.13,"itr":29.0,"ar":25953.95},{"ci":"375142","ri":"375143","ti":"375150","v":1385191,"p":148.95,"sc":2,"cc":2,"mdi":1.35,"pbs":{},"rbs":{"Оператор мобильной связи":{}},"cbs":{"Оператор мобильной связи":{"lpr":0.0,"lq":0.0,"spr":0.0,"sq":0.0}},"wi":38.66,"itr":29.0,"ar":13452.01},{"ci":"375142","ri":"375143","ti":"375148","v":16009867,"p":117.02,"sc":21,"cc":15,"mdi":3.3,"pbs":{},"rbs":{"Оператор мобильной связи":{}},"cbs":{"Оператор мобильной связи":{"lpr":0.0,"lq":0.0,"spr":0.0,"sq":0.0}},"wi":61.68,"itr":29.0,"ar":17571.89},{"ci":"15905","ri":"3042","ti":"3043","v":176740218,"p":199.16,"sc":76,"cc":63,"mdi":4.75,"pbs":{},"rbs":{"Оператор мобильной связи":{}},"cbs":{"Оператор мобильной связи":{"lpr":0.0,"lq":0.0,"spr":0.0,"sq":0.0}},"wi":132.97,"itr":34.0,"ar":6836.0},{"ci":"15905","ri":"3042","ti":"15955","v":19054709,"p":316.96,"sc":7,"cc":7,"mdi":7.46,"pbs":{},"rbs":{"Оператор мобильной связи":{}},"cbs":{"Оператор мобильной связи":{"lpr":0.0,"lq":0.0,"spr":0.0,"sq":0.0}},"wi":128.02,"itr":34.0,"ar":33554.85},{"ci":"15905","ri":"3042","ti":"3052","v":31384250,"p":244.42,"sc":13,"cc":13,"mdi":6.45,"pbs":{},"rbs":{"Оператор мобильной связи":{}},"cbs":{"Оператор мобильной связи":{"lpr":0.0,"lq":0.0,"spr":0.0,"sq":0.0}},"wi":119.43,"itr":34.0,"ar":256541.0},{"ci":"15905","ri":"3042","ti":"423027","v":2171116,"p":505.44,"sc":4,"cc":4,"mdi":3.37,"pbs":{},"rbs":{"Оператор мобильной связи":{}},"cbs":{"Оператор мобильной связи":{"lpr":0.0,"lq":0.0,"spr":0.0,"sq":0.0}},"wi":127.32,"itr":34.0,"ar":45746.0},{"ci":"15905","ri":"3042","ti":"422980","v":3336050,"p":415.13,"sc":3,"cc":3,"mdi":3.65,"pbs":{},"rbs":{"Оператор мобильной связи":{}},"cbs":{"Оператор мобильной связи":{"lpr":0.0,"lq":0.0,"spr":0.0,"sq":0.0}},"wi":108.54,"itr":34.0,"ar":19799.32},{"ci":"15905","ri":"3042","ti":"3044","v":109141564,"p":297.43,"sc":40,"cc":38,"mdi":10.8,"pbs":{},"rbs":{"Оператор мобильной связи":{}},"cbs":{"Оператор мобильной связи":{"lpr":0.0,"lq":0.0,"spr":0.0,"sq":0.0}},"wi":100.43,"itr":34.0,"ar":30438.91},{"ci":"15905","ri":"3042","ti":"3053","v":16759139,"p":230.69,"sc":6,"cc":6,"mdi":6.82,"pbs":{},"rbs":{"Оператор мобильной связи":{}},"cbs":{"Оператор мобильной связи":{"lpr":0.0,"lq":0.0,"spr":0.0,"sq":0.0}},"wi":97.28,"itr":34.0,"ar":18734.4},{"ci":"15905","ri":"3042","ti":"3049","v":21215135,"p":321.4,"sc":9,"cc":9,"mdi":7.94,"pbs":{},"rbs":{"Оператор мобильной связи":{}},"cbs":{"Оператор мобильной связи":{"lpr":0.0,"lq":0.0,"spr":0.0,"sq":0.0}},"wi":94.66,"itr":34.0,"ar":33220.0},{"ci":"15905","ri":"3042","ti":"15957","v":10356182,"p":239.95,"sc":6,"cc":6,"mdi":4.6,"pbs":{},"rbs":{"Оператор мобильной связи":{}},"cbs":{"Оператор мобильной связи":{"lpr":0.0,"lq":0.0,"spr":0.0,"sq":0.0}},"wi":70.58,"itr":34.0,"ar":14310.4},{"ci":"15905","ri":"3042","ti":"422042","v":5218462,"p":295.38,"sc":6,"cc":6,"mdi":3.5,"pbs":{},"rbs":{"Оператор мобильной связи":{}},"cbs":{"Оператор мобильной связи":{"lpr":0.0,"lq":0.0,"spr":0.0,"sq":0.0}},"wi":120.4,"itr":34.0,"ar":57109.0},{"ci":"15905","ri":"3042","ti":"3051","v":11159412,"p":418.27,"sc":9,"cc":9,"mdi":5.79,"pbs":{},"rbs":{"Оператор мобильной связи":{}},"cbs":{"Оператор мобильной связи":{"lpr":0.0,"lq":0.0,"spr":0.0,"sq":0.0}},"wi":96.23,"itr":34.0,"ar":19167.75},{"ci":"15905","ri":"3042","ti":"422492","v":15424633,"p":385.43,"sc":11,"cc":11,"mdi":6.97,"pbs":{},"rbs":{"Оператор мобильной связи":{}},"cbs":{"Оператор мобильной связи":{"lpr":0.0,"lq":0.0,"spr":0.0,"sq":0.0}},"wi":153.98,"itr":34.0,"ar":38737.65},{"ci":"15905","ri":"3042","ti":"422977","v":5156573,"p":183.32,"sc":2,"cc":2,"mdi":3.83,"pbs":{},"rbs":{"Оператор мобильной связи":{}},"cbs":{"Оператор мобильной связи":{"lpr":0.0,"lq":0.0,"spr":0.0,"sq":0.0}},"wi":93.35,"itr":34.0,"ar":15561.0},{"ci":"15905","ri":"3042","ti":"3046","v":11341732,"p":531.97,"sc":10,"cc":10,"mdi":6.52,"pbs":{},"rbs":{"Оператор мобильной связи":{}},"cbs":{"Оператор мобильной связи":{"lpr":0.0,"lq":0.0,"spr":0.0,"sq":0.0}},"wi":76.09,"itr":34.0,"ar":18058.95},{"ci":"15905","ri":"3042","ti":"422529","v":9198462,"p":180.51,"sc":5,"cc":5,"mdi":5.49,"pbs":{},"rbs":{"Оператор мобильной связи":{}},"cbs":{"Оператор мобильной связи":{"lpr":0.0,"lq":0.0,"spr":0.0,"sq":0.0}},"wi":135.19,"itr":34.0,"ar":39043.0},{"ci":"15905","ri":"3042","ti":"3045","v":32344236,"p":381.59,"sc":21,"cc":19,"mdi":7.01,"pbs":{},"rbs":{"Оператор мобильной связи":{}},"cbs":{"Оператор мобильной связи":{"lpr":0.0,"lq":0.0,"spr":0.0,"sq":0.0}},"wi":75.37,"itr":34.0,"ar":23103.85},{"ci":"15905","ri":"3042","ti":"15954","v":7321630,"p":413.13,"sc":6,"cc":6,"mdi":6.92,"pbs":{},"rbs":{"Оператор мобильной связи":{}},"cbs":{"Оператор мобильной связи":{"lpr":0.0,"lq":0.0,"spr":0.0,"sq":0.0}},"wi":94.83,"itr":34.0,"ar":17295.0},{"ci":"15905","ri":"3042","ti":"422022","v":3855700,"p":305.0,"sc":3,"cc":3,"mdi":4.11,"pbs":{},"rbs":{"Оператор мобильной связи":{}},"cbs":{"Оператор мобильной связи":{"lpr":0.0,"lq":0.0,"spr":0.0,"sq":0.0}},"wi":103.68,"itr":34.0,"ar":25431.0},{"ci":"15905","ri":"3042","ti":"3047","v":23927870,"p":606.11,"sc":22,"cc":22,"mdi":6.47,"pbs":{},"rbs":{"Оператор мобильной связи":{}},"cbs":{"Оператор мобильной связи":{"lpr":0.0,"lq":0.0,"spr":0.0,"sq":0.0}},"wi":146.31,"itr":34.0,"ar":25499.0},{"ci":"15905","ri":"3042","ti":"3050","v":14516145,"p":451.14,"sc":8,"cc":8,"mdi":6.9,"pbs":{},"rbs":{"Оператор мобильной связи":{}},"cbs":{"Оператор мобильной связи":{"lpr":0.0,"lq":0.0,"spr":0.0,"sq":0.0}},"wi":95.22,"itr":34.0,"ar":39335.1},{"ci":"15905","ri":"3042","ti":"422493","v":103629,"p":400.0,"sc":1,"cc":1,"mdi":2.93,"pbs":{},"rbs":{"Оператор мобильной связи":{}},"cbs":{"Оператор мобильной связи":{"lpr":0.0,"lq":0.0,"spr":0.0,"sq":0.0}},"wi":82.3,"itr":34.0,"ar":23602.68},{"ci":"15905","ri":"3042","ti":"3048","v":37202588,"p":297.27,"sc":16,"cc":16,"mdi":6.23,"pbs":{},"rbs":{"Оператор мобильной связи":{}},"cbs":{"Оператор мобильной связи":{"lpr":0.0,"lq":0.0,"spr":0.0,"sq":0.0}},"wi":105.14,"itr":34.0,"ar":24854.55},{"ci":"422043","ri":"422044","ti":"422046","v":23812403,"p":333.52,"sc":16,"cc":15,"mdi":4.23,"pbs":{},"rbs":{"Оператор мобильной связи":{}},"cbs":{"Оператор мобильной связи":{"lpr":0.0,"lq":0.0,"spr":0.0,"sq":0.0}},"wi":84.34,"itr":24.0,"ar":28569.08},{"ci":"422043","ri":"422044","ti":"422051","v":277530,"p":397.35,"sc":4,"cc":4,"mdi":2.46,"pbs":{},"rbs":{"Оператор мобильной связи":{}},"cbs":{"Оператор мобильной связи":{"lpr":0.0,"lq":0.0,"spr":0.0,"sq":0.0}},"wi":24.38,"itr":24.0,"ar":6327.98},{"ci":"422043","ri":"422044","ti":"422050","v":247534,"p":400.0,"sc":3,"cc":3,"mdi":2.09,"pbs":{},"rbs":{"Оператор мобильной связи":{}},"cbs":{"Оператор мобильной связи":{"lpr":0.0,"lq":0.0,"spr":0.0,"sq":0.0}},"wi":29.22,"itr":24.0,"ar":7981.58},{"ci":"422043","ri":"422044","ti":"422495","v":342131,"p":478.66,"sc":4,"cc":4,"mdi":2.05,"pbs":{},"rbs":{"Оператор мобильной связи":{}},"cbs":{"Оператор мобильной связи":{"lpr":0.0,"lq":0.0,"spr":0.0,"sq":0.0}},"wi":42.83,"itr":24.0,"ar":5966.73},{"ci":"422043","ri":"422044","ti":"422047","v":9730991,"p":171.17,"sc":8,"cc":8,"mdi":2.92,"pbs":{},"rbs":{"Оператор мобильной связи":{}},"cbs":{"Оператор мобильной связи":{"lpr":0.0,"lq":0.0,"spr":0.0,"sq":0.0}},"wi":62.99,"itr":24.0,"ar":22887.9},{"ci":"422043","ri":"422045","ti":"422049","v":185539,"p":507.9,"sc":4,"cc":4,"mdi":1.62,"pbs":{},"rbs":{"Оператор мобильной связи":{}},"cbs":{"Оператор мобильной связи":{"lpr":0.0,"lq":0.0,"spr":0.0,"sq":0.0}},"wi":53.39,"itr":29.0,"ar":9680.29},{"ci":"422043","ri":"422045","ti":"422048","v":162720,"p":443.84,"sc":3,"cc":3,"mdi":1.42,"pbs":{},"rbs":{"Оператор мобильной связи":{}},"cbs":{"Оператор мобильной связи":{"lpr":0.0,"lq":0.0,"spr":0.0,"sq":0.0}},"wi":34.68,"itr":29.0,"ar":8574.18},{"ci":"422043","ri":"422045","ti":"422997","v":203973,"p":220.07,"sc":2,"cc":2,"mdi":1.67,"pbs":{},"rbs":{"Оператор мобильной связи":{}},"cbs":{"Оператор мобильной связи":{"lpr":0.0,"lq":0.0,"spr":0.0,"sq":0.0}},"wi":43.6,"itr":29.0,"ar":7446.38},{"ci":"422043","ri":"422045","ti":"422515","v":60397,"p":329.21,"sc":2,"cc":2,"mdi":2.24,"pbs":{},"rbs":{"Оператор мобильной связи":{}},"cbs":{"Оператор мобильной связи":{"lpr":0.0,"lq":0.0,"spr":0.0,"sq":0.0}},"wi":32.45,"itr":29.0,"ar":5741.82},{"ci":"422043","ri":"422045","ti":"422052","v":148298,"p":344.13,"sc":2,"cc":2,"mdi":1.17,"pbs":{},"rbs":{"Оператор мобильной связи":{}},"cbs":{"Оператор мобильной связи":{"lpr":0.0,"lq":0.0,"spr":0.0,"sq":0.0}},"wi":40.95,"itr":29.0,"ar":6648.26},{"ci":"423255","ri":"423256","ti":"423257","v":40910248,"p":155.7,"sc":11,"cc":11,"mdi":5.22,"pbs":{},"rbs":{"Оператор мобильной связи":{}},"cbs":{"Оператор мобильной связи":{"lpr":0.0,"lq":0.0,"spr":0.0,"sq":0.0}},"wi":108.24,"itr":51.0,"ar":88212.0},{"ci":"423255","ri":"423256","ti":"423259","v":37936,"p":1000.0,"sc":1,"cc":1,"mdi":0.3,"pbs":{},"rbs":{"Оператор мобильной связи":{}},"cbs":{"Оператор мобильной связи":{"lpr":0.0,"lq":0.0,"spr":0.0,"sq":0.0}},"wi":119.07,"itr":51.0,"ar":36304.8},{"ci":"423255","ri":"423256","ti":"423260","v":572669,"p":195.63,"sc":2,"cc":2,"mdi":1.15,"pbs":{},"rbs":{"Оператор мобильной связи":{}},"cbs":{"Оператор мобильной связи":{"lpr":0.0,"lq":0.0,"spr":0.0,"sq":0.0}},"wi":80.57,"itr":51.0,"ar":44569.0},{"ci":"423255","ri":"423256","ti":"423258","v":1028623,"p":357.34,"sc":3,"cc":3,"mdi":2.1,"pbs":{},"rbs":{"Оператор мобильной связи":{}},"cbs":{"Оператор мобильной связи":{"lpr":0.0,"lq":0.0,"spr":0.0,"sq":0.0}},"wi":72.56,"itr":51.0,"ar":41191.61},{"ci":"423475","ri":"423476","ti":"423480","v":84289,"p":123.69,"sc":2,"cc":2,"mdi":1.66,"pbs":{},"rbs":{"Оператор мобильной связи":{}},"cbs":{"Оператор мобильной связи":{"lpr":0.0,"lq":0.0,"spr":0.0,"sq":0.0}},"wi":34.04,"itr":34.0,"ar":21688.0},{"ci":"423475","ri":"423476","ti":"423478","v":177248,"p":317.73,"sc":3,"cc":3,"mdi":2.53,"pbs":{},"rbs":{"Оператор мобильной связи":{}},"cbs":{"Оператор мобильной связи":{"lpr":0.0,"lq":0.0,"spr":0.0,"sq":0.0}},"wi":57.24,"itr":34.0,"ar":34843.0},{"ci":"423475","ri":"423476","ti":"423477","v":11797216,"p":21.58,"sc":4,"cc":4,"mdi":3.75,"pbs":{},"rbs":{"Оператор мобильной связи":{}},"cbs":{"Оператор мобильной связи":{"lpr":0.0,"lq":0.0,"spr":0.0,"sq":0.0}},"wi":64.91,"itr":34.0,"ar":73287.9},{"ci":"423475","ri":"423476","ti":"423479","v":73695,"p":182.0,"sc":1,"cc":1,"mdi":2.15,"pbs":{},"rbs":{"Оператор мобильной связи":{}},"cbs":{"Оператор мобильной связи":{"lpr":0.0,"lq":0.0,"spr":0.0,"sq":0.0}},"wi":30.77,"itr":34.0,"ar":22884.0},{"ci":"7060","ri":"7064","ti":"422505","v":64081,"p":116.13,"sc":3,"cc":3,"mdi":0.84,"pbs":{},"rbs":{"Оператор мобильной связи":{}},"cbs":{"Оператор мобильной связи":{"lpr":0.0,"lq":0.0,"spr":0.0,"sq":0.0}},"wi":14.62,"itr":23.0,"ar":4989.43},{"ci":"7060","ri":"7064","ti":"422507","v":154875,"p":455.46,"sc":3,"cc":3,"mdi":2.09,"pbs":{},"rbs":{"Оператор мобильной связи":{}},"cbs":{"Оператор мобильной связи":{"lpr":0.0,"lq":0.0,"spr":0.0,"sq":0.0}},"wi":35.23,"itr":23.0,"ar":3514.35},{"ci":"7060","ri":"7064","ti":"7083","v":290898,"p":1237.95,"sc":4,"cc":4,"mdi":2.09,"pbs":{},"rbs":{"Оператор мобильной связи":{}},"cbs":{"Оператор мобильной связи":{"lpr":0.0,"lq":0.0,"spr":0.0,"sq":0.0}},"wi":37.42,"itr":23.0,"ar":12606.21},{"ci":"7060","ri":"7064","ti":"7082","v":128313,"p":2588.47,"sc":2,"cc":2,"mdi":2.01,"pbs":{},"rbs":{"Оператор мобильной связи":{}},"cbs":{"Оператор мобильной связи":{"lpr":0.0,"lq":0.0,"spr":0.0,"sq":0.0}},"wi":40.77,"itr":23.0,"ar":12648.21},{"ci":"7060","ri":"7065","ti":"7087","v":255669,"p":1232.08,"sc":4,"cc":4,"mdi":2.45,"pbs":{},"rbs":{"Оператор мобильной связи":{}},"cbs":{"Оператор мобильной связи":{"lpr":0.0,"lq":0.0,"spr":0.0,"sq":0.0}},"wi":38.2,"itr":25.0,"ar":18560.78},{"ci":"7060","ri":"7065","ti":"7084","v":15949761,"p":57.24,"sc":5,"cc":5,"mdi":2.97,"pbs":{},"rbs":{"Оператор мобильной связи":{}},"cbs":{"Оператор мобильной связи":{"lpr":0.0,"lq":0.0,"spr":0.0,"sq":0.0}},"wi":54.97,"itr":25.0,"ar":8997.06},{"ci":"7060","ri":"7065","ti":"7086","v":669695,"p":675.32,"sc":4,"cc":4,"mdi":2.02,"pbs":{},"rbs":{"Оператор мобильной связи":{}},"cbs":{"Оператор мобильной связи":{"lpr":0.0,"lq":0.0,"spr":0.0,"sq":0.0}},"wi":38.82,"itr":25.0,"ar":9891.21},{"ci":"7060","ri":"7065","ti":"422526","v":269254,"p":446.84,"sc":2,"cc":2,"mdi":1.98,"pbs":{},"rbs":{"Оператор мобильной связи":{}},"cbs":{"Оператор мобильной связи":{"lpr":0.0,"lq":0.0,"spr":0.0,"sq":0.0}},"wi":40.17,"itr":25.0,"ar":7484.14},{"ci":"7060","ri":"7065","ti":"7085","v":193150,"p":2351.49,"sc":4,"cc":4,"mdi":2.77,"pbs":{},"rbs":{"Оператор мобильной связи":{}},"cbs":{"Оператор мобильной связи":{"lpr":0.0,"lq":0.0,"spr":0.0,"sq":0.0}},"wi":37.43,"itr":25.0,"ar":10880.24},{"ci":"7060","ri":"7062","ti":"7073","v":57797367,"p":60.24,"sc":11,"cc":11,"mdi":4.32,"pbs":{},"rbs":{"Оператор мобильной связи":{}},"cbs":{"Оператор мобильной связи":{"lpr":0.0,"lq":0.0,"spr":0.0,"sq":0.0}},"wi":66.49,"itr":20.0,"ar":19361.0},{"ci":"7060","ri":"7062","ti":"7071","v":5079798,"p":141.93,"sc":10,"cc":9,"mdi":3.33,"pbs":{},"rbs":{"Оператор мобильной связи":{}},"cbs":{"Оператор мобильной связи":{"lpr":0.0,"lq":0.0,"spr":0.0,"sq":0.0}},"wi":48.24,"itr":20.0,"ar":20529.0},{"ci":"7060","ri":"7062","ti":"7069","v":703069,"p":554.53,"sc":5,"cc":5,"mdi":2.19,"pbs":{},"rbs":{"Оператор мобильной связи":{}},"cbs":{"Оператор мобильной связи":{"lpr":0.0,"lq":0.0,"spr":0.0,"sq":0.0}},"wi":32.49,"itr":20.0,"ar":9618.0},{"ci":"7060","ri":"7062","ti":"7072","v":644692,"p":1835.54,"sc":13,"cc":10,"mdi":3.66,"pbs":{},"rbs":{"Оператор мобильной связи":{}},"cbs":{"Оператор мобильной связи":{"lpr":0.0,"lq":0.0,"spr":0.0,"sq":0.0}},"wi":78.29,"itr":20.0,"ar":19281.83},{"ci":"7060","ri":"7062","ti":"7070","v":3261838,"p":21.94,"sc":7,"cc":7,"mdi":0.93,"pbs":{},"rbs":{"Оператор мобильной связи":{}},"cbs":{"Оператор мобильной связи":{"lpr":0.0,"lq":0.0,"spr":0.0,"sq":0.0}},"wi":7.39,"itr":20.0,"ar":1517.29},{"ci":"7060","ri":"7062","ti":"7075","v":408675,"p":590.44,"sc":3,"cc":3,"mdi":1.82,"pbs":{},"rbs":{"Оператор мобильной связи":{}},"cbs":{"Оператор мобильной связи":{"lpr":0.0,"lq":0.0,"spr":0.0,"sq":0.0}},"wi":63.54,"itr":20.0,"ar":12809.63},{"ci":"7060","ri":"7062","ti":"7074","v":6137918,"p":30.25,"sc":4,"cc":4,"mdi":1.36,"pbs":{},"rbs":{"Оператор мобильной связи":{}},"cbs":{"Оператор мобильной связи":{"lpr":0.0,"lq":0.0,"spr":0.0,"sq":0.0}},"wi":52.72,"itr":20.0,"ar":9346.05},{"ci":"7060","ri":"7061","ti":"7068","v":300604,"p":132.69,"sc":2,"cc":2,"mdi":1.73,"pbs":{},"rbs":{"Оператор мобильной связи":{}},"cbs":{"Оператор мобильной связи":{"lpr":0.0,"lq":0.0,"spr":0.0,"sq":0.0}},"wi":15.5,"itr":20.0,"ar":4253.45},{"ci":"7060","ri":"7061","ti":"7066","v":5106722,"p":511.77,"sc":5,"cc":5,"mdi":3.37,"pbs":{},"rbs":{"Оператор мобильной связи":{}},"cbs":{"Оператор мобильной связи":{"lpr":0.0,"lq":0.0,"spr":0.0,"sq":0.0}},"wi":79.93,"itr":20.0,"ar":12398.16},{"ci":"7060","ri":"7061","ti":"7067","v":786410,"p":584.55,"sc":2,"cc":2,"mdi":2.35,"pbs":{},"rbs":{"Оператор мобильной связи":{}},"cbs":{"Оператор мобильной связи":{"lpr":0.0,"lq":0.0,"spr":0.0,"sq":0.0}},"wi":73.23,"itr":20.0,"ar":9109.57},{"ci":"7060","ri":"7063","ti":"7076","v":247064934,"p":30.14,"sc":13,"cc":11,"mdi":6.02,"pbs":{},"rbs":{"Оператор мобильной связи":{}},"cbs":{"Оператор мобильной связи":{"lpr":0.0,"lq":0.0,"spr":0.0,"sq":0.0}},"wi":57.77,"itr":25.0,"ar":19356.0},{"ci":"7060","ri":"7063","ti":"7081","v":301622,"p":286.88,"sc":3,"cc":3,"mdi":1.05,"pbs":{},"rbs":{"Оператор мобильной связи":{}},"cbs":{"Оператор мобильной связи":{"lpr":0.0,"lq":0.0,"spr":0.0,"sq":0.0}},"wi":26.64,"itr":25.0,"ar":26881.05},{"ci":"7060","ri":"7063","ti":"7080","v":206970,"p":595.96,"sc":3,"cc":3,"mdi":1.14,"pbs":{},"rbs":{"Оператор мобильной связи":{}},"cbs":{"Оператор мобильной связи":{"lpr":0.0,"lq":0.0,"spr":0.0,"sq":0.0}},"wi":30.6,"itr":25.0,"ar":5486.8},{"ci":"7060","ri":"7063","ti":"7079","v":163900,"p":280.46,"sc":3,"cc":3,"mdi":1.12,"pbs":{},"rbs":{"Оператор мобильной связи":{}},"cbs":{"Оператор мобильной связи":{"lpr":0.0,"lq":0.0,"spr":0.0,"sq":0.0}},"wi":31.57,"itr":25.0,"ar":6073.51},{"ci":"7060","ri":"7063","ti":"7078","v":134499,"p":495.64,"sc":3,"cc":3,"mdi":0.95,"pbs":{},"rbs":{"Оператор мобильной связи":{}},"cbs":{"Оператор мобильной связи":{"lpr":0.0,"lq":0.0,"spr":0.0,"sq":0.0}},"wi":23.29,"itr":25.0,"ar":3536.54},{"ci":"7060","ri":"7063","ti":"7077","v":17441431,"p":37.98,"sc":5,"cc":5,"mdi":2.56,"pbs":{},"rbs":{"Оператор мобильной связи":{}},"cbs":{"Оператор мобильной связи":{"lpr":0.0,"lq":0.0,"spr":0.0,"sq":0.0}},"wi":37.38,"itr":25.0,"ar":6000.91},{"ci":"422362","ri":"422363","ti":"422373","v":2196318,"p":235.13,"sc":3,"cc":3,"mdi":0.88,"pbs":{},"rbs":{"Оператор мобильной связи":{}},"cbs":{"Оператор мобильной связи":{"lpr":0.0,"lq":0.0,"spr":0.0,"sq":0.0}},"wi":77.72,"itr":30.0,"ar":19398.51},{"ci":"422362","ri":"422363","ti":"422371","v":5933945,"p":249.67,"sc":6,"cc":6,"mdi":2.79,"pbs":{},"rbs":{"Оператор мобильной связи":{}},"cbs":{"Оператор мобильной связи":{"lpr":0.0,"lq":0.0,"spr":0.0,"sq":0.0}},"wi":74.62,"itr":30.0,"ar":13397.58},{"ci":"422362","ri":"422363","ti":"422366","v":51726329,"p":311.99,"sc":42,"cc":32,"mdi":5.03,"pbs":{},"rbs":{"Оператор мобильной связи":{}},"cbs":{"Оператор мобильной связи":{"lpr":0.0,"lq":0.0,"spr":0.0,"sq":0.0}},"wi":89.8,"itr":30.0,"ar":36528.0},{"ci":"422362","ri":"422363","ti":"422369","v":5573680,"p":359.9,"sc":8,"cc":8,"mdi":3.16,"pbs":{},"rbs":{"Оператор мобильной связи":{}},"cbs":{"Оператор мобильной связи":{"lpr":0.0,"lq":0.0,"spr":0.0,"sq":0.0}},"wi":60.97,"itr":30.0,"ar":20651.4},{"ci":"422362","ri":"422363","ti":"422365","v":114983142,"p":281.27,"sc":59,"cc":56,"mdi":4.45,"pbs":{},"rbs":{"Оператор мобильной связи":{}},"cbs":{"Оператор мобильной связи":{"lpr":0.0,"lq":0.0,"spr":0.0,"sq":0.0}},"wi":105.21,"itr":30.0,"ar":68370.44},{"ci":"422362","ri":"422364","ti":"422367","v":38319150,"p":180.22,"sc":21,"cc":19,"mdi":3.82,"pbs":{},"rbs":{"Оператор мобильной связи":{}},"cbs":{"Оператор мобильной связи":{"lpr":0.0,"lq":0.0,"spr":0.0,"sq":0.0}},"wi":81.74,"itr":30.0,"ar":25531.0},{"ci":"422362","ri":"422364","ti":"422372","v":6813968,"p":166.89,"sc":11,"cc":9,"mdi":2.67,"pbs":{},"rbs":{"Оператор мобильной связи":{}},"cbs":{"Оператор мобильной связи":{"lpr":0.0,"lq":0.0,"spr":0.0,"sq":0.0}},"wi":60.41,"itr":30.0,"ar":14493.0},{"ci":"422362","ri":"422364","ti":"422368","v":5583431,"p":403.01,"sc":8,"cc":8,"mdi":2.54,"pbs":{},"rbs":{"Оператор мобильной связи":{}},"cbs":{"Оператор мобильной связи":{"lpr":0.0,"lq":0.0,"spr":0.0,"sq":0.0}},"wi":77.97,"itr":30.0,"ar":23667.0},{"ci":"422362","ri":"422364","ti":"422370","v":6282621,"p":291.9,"sc":16,"cc":13,"mdi":2.46,"pbs":{},"rbs":{"Оператор мобильной связи":{}},"cbs":{"Оператор мобильной связи":{"lpr":0.0,"lq":0.0,"spr":0.0,"sq":0.0}},"wi":70.43,"itr":30.0,"ar":17246.0},{"ci":"423554","ri":"423555","ti":"423557","v":46323613,"p":120.96,"sc":18,"cc":18,"mdi":6.2,"pbs":{},"rbs":{"Оператор мобильной связи":{}},"cbs":{"Оператор мобильной связи":{"lpr":0.0,"lq":0.0,"spr":0.0,"sq":0.0}},"wi":150.0,"itr":32.0,"ar":371488.0},{"ci":"423554","ri":"423555","ti":"423558","v":1205570,"p":622.35,"sc":5,"cc":5,"mdi":2.7,"pbs":{},"rbs":{"Оператор мобильной связи":{}},"cbs":{"Оператор мобильной связи":{"lpr":0.0,"lq":0.0,"spr":0.0,"sq":0.0}},"wi":64.2,"itr":32.0,"ar":16257.0},{"ci":"423554","ri":"423555","ti":"423563","v":385520,"p":941.66,"sc":5,"cc":5,"mdi":3.32,"pbs":{},"rbs":{"Оператор мобильной связи":{}},"cbs":{"Оператор мобильной связи":{"lpr":0.0,"lq":0.0,"spr":0.0,"sq":0.0}},"wi":150.93,"itr":32.0,"ar":165475.01},{"ci":"423554","ri":"423555","ti":"423559","v":2357746,"p":155.45,"sc":2,"cc":2,"mdi":1.39,"pbs":{},"rbs":{"Оператор мобильной связи":{}},"cbs":{"Оператор мобильной связи":{"lpr":0.0,"lq":0.0,"spr":0.0,"sq":0.0}},"wi":170.37,"itr":32.0,"ar":206727.0},{"ci":"423554","ri":"423555","ti":"423561","v":2101192,"p":268.33,"sc":4,"cc":4,"mdi":3.81,"pbs":{},"rbs":{"Оператор мобильной связи":{}},"cbs":{"Оператор мобильной связи":{"lpr":0.0,"lq":0.0,"spr":0.0,"sq":0.0}},"wi":177.29,"itr":32.0,"ar":214548.0},{"ci":"423554","ri":"423555","ti":"423562","v":1394382,"p":290.82,"sc":3,"cc":3,"mdi":4.36,"pbs":{},"rbs":{"Оператор мобильной связи":{}},"cbs":{"Оператор мобильной связи":{"lpr":0.0,"lq":0.0,"spr":0.0,"sq":0.0}},"wi":122.87,"itr":32.0,"ar":144391.06},{"ci":"423554","ri":"423555","ti":"423560","v":1749585,"p":354.13,"sc":4,"cc":4,"mdi":3.61,"pbs":{},"rbs":{"Оператор мобильной связи":{}},"cbs":{"Оператор мобильной связи":{"lpr":0.0,"lq":0.0,"spr":0.0,"sq":0.0}},"wi":139.78,"itr":32.0,"ar":120972.0},{"ci":"423554","ri":"423555","ti":"423556","v":18529475,"p":211.73,"sc":11,"cc":10,"mdi":5.08,"pbs":{},"rbs":{"Оператор мобильной связи":{}},"cbs":{"Оператор мобильной связи":{"lpr":0.0,"lq":0.0,"spr":0.0,"sq":0.0}},"wi":133.29,"itr":32.0,"ar":286485.0},{"ci":"422187","ri":"422188","ti":"422942","v":110443,"p":665.51,"sc":3,"cc":3,"mdi":1.88,"pbs":{},"rbs":{"Оператор мобильной связи":{}},"cbs":{"Оператор мобильной связи":{"lpr":0.0,"lq":0.0,"spr":0.0,"sq":0.0}},"wi":30.05,"itr":23.0,"ar":6502.65},{"ci":"422187","ri":"422188","ti":"422189","v":54710005,"p":80.44,"sc":10,"cc":10,"mdi":4.2,"pbs":{},"rbs":{"Оператор мобильной связи":{}},"cbs":{"Оператор мобильной связи":{"lpr":0.0,"lq":0.0,"spr":0.0,"sq":0.0}},"wi":59.46,"itr":23.0,"ar":14656.0},{"ci":"422187","ri":"422188","ti":"422193","v":968320,"p":350.0,"sc":2,"cc":2,"mdi":2.83,"pbs":{},"rbs":{"Оператор мобильной связи":{}},"cbs":{"Оператор мобильной связи":{"lpr":0.0,"lq":0.0,"spr":0.0,"sq":0.0}},"wi":59.58,"itr":23.0,"ar":19657.75},{"ci":"422187","ri":"422188","ti":"422191","v":672286,"p":236.74,"sc":3,"cc":3,"mdi":2.03,"pbs":{},"rbs":{"Оператор мобильной связи":{}},"cbs":{"Оператор мобильной связи":{"lpr":0.0,"lq":0.0,"spr":0.0,"sq":0.0}},"wi":28.02,"itr":23.0,"ar":4651.5},{"ci":"422187","ri":"422188","ti":"422979","v":115370,"p":764.28,"sc":3,"cc":3,"mdi":1.95,"pbs":{},"rbs":{"Оператор мобильной связи":{}},"cbs":{"Оператор мобильной связи":{"lpr":0.0,"lq":0.0,"spr":0.0,"sq":0.0}},"wi":32.55,"itr":23.0,"ar":7081.85},{"ci":"422187","ri":"422188","ti":"422192","v":722890,"p":207.14,"sc":4,"cc":4,"mdi":1.91,"pbs":{},"rbs":{"Оператор мобильной связи":{}},"cbs":{"Оператор мобильной связи":{"lpr":0.0,"lq":0.0,"spr":0.0,"sq":0.0}},"wi":28.37,"itr":23.0,"ar":9534.02},{"ci":"422187","ri":"422188","ti":"422195","v":922878,"p":89.7,"sc":4,"cc":4,"mdi":1.81,"pbs":{},"rbs":{"Оператор мобильной связи":{}},"cbs":{"Оператор мобильной связи":{"lpr":0.0,"lq":0.0,"spr":0.0,"sq":0.0}},"wi":22.87,"itr":23.0,"ar":6745.69},{"ci":"422187","ri":"422188","ti":"422194","v":616976,"p":122.15,"sc":3,"cc":3,"mdi":1.66,"pbs":{},"rbs":{"Оператор мобильной связи":{}},"cbs":{"Оператор мобильной связи":{"lpr":0.0,"lq":0.0,"spr":0.0,"sq":0.0}},"wi":29.54,"itr":23.0,"ar":6207.6},{"ci":"422187","ri":"422188","ti":"422190","v":5469797,"p":101.38,"sc":5,"cc":5,"mdi":2.35,"pbs":{},"rbs":{"Оператор мобильной связи":{}},"cbs":{"Оператор мобильной связи":{"lpr":0.0,"lq":0.0,"spr":0.0,"sq":0.0}},"wi":54.27,"itr":23.0,"ar":21291.48},{"ci":"325645","ri":"325646","ti":"422943","v":392913,"p":222.06,"sc":7,"cc":7,"mdi":2.82,"pbs":{},"rbs":{"Оператор мобильной связи":{}},"cbs":{"Оператор мобильной связи":{"lpr":0.0,"lq":0.0,"spr":0.0,"sq":0.0}},"wi":40.37,"itr":1.0,"ar":10755.0},{"ci":"325645","ri":"325646","ti":"325648","v":4250272,"p":43.01,"sc":12,"cc":12,"mdi":2.36,"pbs":{},"rbs":{"Оператор мобильной связи":{}},"cbs":{"Оператор мобильной связи":{"lpr":0.0,"lq":0.0,"spr":0.0,"sq":0.0}},"wi":25.95,"itr":1.0,"ar":18501.0},{"ci":"325645","ri":"325646","ti":"422513","v":1164414,"p":59.94,"sc":6,"cc":6,"mdi":2.06,"pbs":{},"rbs":{"Оператор мобильной связи":{}},"cbs":{"Оператор мобильной связи":{"lpr":0.0,"lq":0.0,"spr":0.0,"sq":0.0}},"wi":22.85,"itr":1.0,"ar":10170.0},{"ci":"325645","ri":"325646","ti":"325649","v":1137144,"p":205.35,"sc":10,"cc":10,"mdi":1.61,"pbs":{},"rbs":{"Оператор мобильной связи":{}},"cbs":{"Оператор мобильной связи":{"lpr":0.0,"lq":0.0,"spr":0.0,"sq":0.0}},"wi":24.94,"itr":1.0,"ar":46411.05},{"ci":"325645","ri":"325646","ti":"325647","v":29259917,"p":78.45,"sc":33,"cc":33,"mdi":3.21,"pbs":{},"rbs":{"Оператор мобильной связи":{}},"cbs":{"Оператор мобильной связи":{"lpr":0.0,"lq":0.0,"spr":0.0,"sq":0.0}},"wi":61.55,"itr":1.0,"ar":44315.25},{"ci":"325645","ri":"325646","ti":"422037","v":1176183,"p":96.29,"sc":6,"cc":6,"mdi":2.79,"pbs":{},"rbs":{"Оператор мобильной связи":{}},"cbs":{"Оператор мобильной связи":{"lpr":0.0,"lq":0.0,"spr":0.0,"sq":0.0}},"wi":49.32,"itr":1.0,"ar":29447.25},{"ci":"325650","ri":"325651","ti":"325652","v":18243960,"p":90.93,"sc":7,"cc":6,"mdi":3.48,"pbs":{},"rbs":{"Оператор мобильной связи":{}},"cbs":{"Оператор мобильной связи":{"lpr":0.0,"lq":0.0,"spr":0.0,"sq":0.0}},"wi":75.85,"itr":15.0,"ar":28530.83},{"ci":"325650","ri":"325651","ti":"325653","v":12754362,"p":57.33,"sc":10,"cc":10,"mdi":2.45,"pbs":{},"rbs":{"Оператор мобильной связи":{}},"cbs":{"Оператор мобильной связи":{"lpr":0.0,"lq":0.0,"spr":0.0,"sq":0.0}},"wi":33.06,"itr":15.0,"ar":7342.39},{"ci":"325650","ri":"325651","ti":"325654","v":806107,"p":330.0,"sc":4,"cc":4,"mdi":2.83,"pbs":{},"rbs":{"Оператор мобильной связи":{}},"cbs":{"Оператор мобильной связи":{"lpr":0.0,"lq":0.0,"spr":0.0,"sq":0.0}},"wi":41.72,"itr":15.0,"ar":14637.33},{"ci":"325650","ri":"325651","ti":"422940","v":371087,"p":250.0,"sc":1,"cc":1,"mdi":2.09,"pbs":{},"rbs":{"Оператор мобильной связи":{}},"cbs":{"Оператор мобильной связи":{"lpr":0.0,"lq":0.0,"spr":0.0,"sq":0.0}},"wi":36.78,"itr":15.0,"ar":6379.67},{"ci":"423581","ri":"423582","ti":"423583","v":8774738,"p":114.82,"sc":5,"cc":3,"mdi":5.0,"pbs":{},"rbs":{"Оператор мобильной связи":{}},"cbs":{"Оператор мобильной связи":{"lpr":0.0,"lq":0.0,"spr":0.0,"sq":0.0}},"wi":113.22,"itr":40.0,"ar":127126.0},{"ci":"423581","ri":"423582","ti":"423585","v":592711,"p":204.8,"sc":2,"cc":2,"mdi":3.14,"pbs":{},"rbs":{"Оператор мобильной связи":{}},"cbs":{"Оператор мобильной связи":{"lpr":0.0,"lq":0.0,"spr":0.0,"sq":0.0}},"wi":109.47,"itr":40.0,"ar":87698.0},{"ci":"423581","ri":"423582","ti":"423584","v":866040,"p":292.36,"sc":3,"cc":3,"mdi":2.32,"pbs":{},"rbs":{"Оператор мобильной связи":{}},"cbs":{"Оператор мобильной связи":{"lpr":0.0,"lq":0.0,"spr":0.0,"sq":0.0}},"wi":167.37,"itr":40.0,"ar":93765.0},{"ci":"422607","ri":"422608","ti":"422633","v":888714,"p":391.31,"sc":5,"cc":5,"mdi":1.44,"pbs":{},"rbs":{"Оператор мобильной связи":{}},"cbs":{"Оператор мобильной связи":{"lpr":0.0,"lq":0.0,"spr":0.0,"sq":0.0}},"wi":47.1,"itr":28.0,"ar":6796.26},{"ci":"422607","ri":"422608","ti":"422629","v":124127,"p":899.65,"sc":3,"cc":3,"mdi":1.2,"pbs":{},"rbs":{"Оператор мобильной связи":{}},"cbs":{"Оператор мобильной связи":{"lpr":0.0,"lq":0.0,"spr":0.0,"sq":0.0}},"wi":21.94,"itr":28.0,"ar":2497.3},{"ci":"422607","ri":"422608","ti":"422630","v":123020,"p":895.86,"sc":3,"cc":3,"mdi":1.09,"pbs":{},"rbs":{"Оператор мобильной связи":{}},"cbs":{"Оператор мобильной связи":{"lpr":0.0,"lq":0.0,"spr":0.0,"sq":0.0}},"wi":22.37,"itr":28.0,"ar":2396.0},{"ci":"422607","ri":"422608","ti":"422620","v":2762943,"p":1028.38,"sc":8,"cc":8,"mdi":3.51,"pbs":{},"rbs":{"Оператор мобильной связи":{}},"cbs":{"Оператор мобильной связи":{"lpr":0.0,"lq":0.0,"spr":0.0,"sq":0.0}},"wi":80.2,"itr":28.0,"ar":15414.0},{"ci":"422607","ri":"422608","ti":"422627","v":787521,"p":743.38,"sc":4,"cc":4,"mdi":1.75,"pbs":{},"rbs":{"Оператор мобильной связи":{}},"cbs":{"Оператор мобильной связи":{"lpr":0.0,"lq":0.0,"spr":0.0,"sq":0.0}},"wi":52.11,"itr":28.0,"ar":7110.6},{"ci":"422607","ri":"422608","ti":"422616","v":915844,"p":1838.25,"sc":8,"cc":8,"mdi":2.54,"pbs":{},"rbs":{"Оператор мобильной связи":{}},"cbs":{"Оператор мобильной связи":{"lpr":0.0,"lq":0.0,"spr":0.0,"sq":0.0}},"wi":73.51,"itr":28.0,"ar":13690.0},{"ci":"422607","ri":"422608","ti":"422617","v":18251948,"p":398.83,"sc":13,"cc":12,"mdi":5.09,"pbs":{},"rbs":{"Оператор мобильной связи":{}},"cbs":{"Оператор мобильной связи":{"lpr":0.0,"lq":0.0,"spr":0.0,"sq":0.0}},"wi":101.91,"itr":28.0,"ar":23415.51},{"ci":"422607","ri":"422608","ti":"422622","v":142510,"p":818.69,"sc":3,"cc":3,"mdi":0.93,"pbs":{},"rbs":{"Оператор мобильной связи":{}},"cbs":{"Оператор мобильной связи":{"lpr":0.0,"lq":0.0,"spr":0.0,"sq":0.0}},"wi":27.76,"itr":28.0,"ar":3097.8},{"ci":"422607","ri":"422608","ti":"422625","v":5142,"p":414.24,"sc":8,"cc":1,"mdi":0.01,"pbs":{},"rbs":{"Оператор мобильной связи":{}},"cbs":{"Оператор мобильной связи":{"lpr":0.0,"lq":0.0,"spr":0.0,"sq":0.0}},"wi":44.76,"itr":28.0,"ar":8524.0},{"ci":"422607","ri":"422609","ti":"422626","v":1270928,"p":430.0,"sc":1,"cc":1,"mdi":2.43,"pbs":{},"rbs":{"Оператор мобильной связи":{}},"cbs":{"Оператор мобильной связи":{"lpr":0.0,"lq":0.0,"spr":0.0,"sq":0.0}},"wi":36.53,"itr":24.0,"ar":5957.8},{"ci":"422607","ri":"422609","ti":"422632","v":8434883,"p":330.48,"sc":7,"cc":7,"mdi":3.96,"pbs":{},"rbs":{"Оператор мобильной связи":{}},"cbs":{"Оператор мобильной связи":{"lpr":0.0,"lq":0.0,"spr":0.0,"sq":0.0}},"wi":109.75,"itr":24.0,"ar":22254.75},{"ci":"422607","ri":"422609","ti":"422614","v":20429913,"p":322.79,"sc":13,"cc":13,"mdi":4.78,"pbs":{},"rbs":{"Оператор мобильной связи":{}},"cbs":{"Оператор мобильной связи":{"lpr":0.0,"lq":0.0,"spr":0.0,"sq":0.0}},"wi":103.3,"itr":24.0,"ar":23638.0},{"ci":"422607","ri":"422609","ti":"422618","v":2527115,"p":595.4,"sc":5,"cc":5,"mdi":2.38,"pbs":{},"rbs":{"Оператор мобильной связи":{}},"cbs":{"Оператор мобильной связи":{"lpr":0.0,"lq":0.0,"spr":0.0,"sq":0.0}},"wi":63.61,"itr":24.0,"ar":13523.64},{"ci":"422607","ri":"422609","ti":"422628","v":518573,"p":1901.15,"sc":9,"cc":7,"mdi":2.81,"pbs":{},"rbs":{"Оператор мобильной связи":{}},"cbs":{"Оператор мобильной связи":{"lpr":0.0,"lq":0.0,"spr":0.0,"sq":0.0}},"wi":61.21,"itr":24.0,"ar":11756.66},{"ci":"422607","ri":"422609","ti":"422619","v":1545923,"p":741.05,"sc":10,"cc":10,"mdi":2.15,"pbs":{},"rbs":{"Оператор мобильной связи":{}},"cbs":{"Оператор мобильной связи":{"lpr":0.0,"lq":0.0,"spr":0.0,"sq":0.0}},"wi":50.92,"itr":24.0,"ar":14215.74},{"ci":"422607","ri":"422610","ti":"422612","v":187841277,"p":356.07,"sc":67,"cc":49,"mdi":6.76,"pbs":{},"rbs":{"Оператор мобильной связи":{}},"cbs":{"Оператор мобильной связи":{"lpr":0.0,"lq":0.0,"spr":0.0,"sq":0.0}},"wi":108.19,"itr":34.0,"ar":23639.0},{"ci":"422607","ri":"422610","ti":"422623","v":6646031,"p":456.19,"sc":8,"cc":6,"mdi":4.5,"pbs":{},"rbs":{"Оператор мобильной связи":{}},"cbs":{"Оператор мобильной связи":{"lpr":0.0,"lq":0.0,"spr":0.0,"sq":0.0}},"wi":92.4,"itr":34.0,"ar":13720.0},{"ci":"422607","ri":"422610","ti":"422621","v":9172143,"p":549.73,"sc":11,"cc":10,"mdi":5.03,"pbs":{},"rbs":{"Оператор мобильной связи":{}},"cbs":{"Оператор мобильной связи":{"lpr":0.0,"lq":0.0,"spr":0.0,"sq":0.0}},"wi":76.26,"itr":34.0,"ar":13716.2},{"ci":"422607","ri":"422610","ti":"422615","v":12950262,"p":445.36,"sc":6,"cc":6,"mdi":4.63,"pbs":{},"rbs":{"Оператор мобильной связи":{}},"cbs":{"Оператор мобильной связи":{"lpr":0.0,"lq":0.0,"spr":0.0,"sq":0.0}},"wi":68.47,"itr":34.0,"ar":15955.42},{"ci":"422607","ri":"422610","ti":"422613","v":5594235,"p":1146.05,"sc":9,"cc":9,"mdi":4.49,"pbs":{},"rbs":{"Оператор мобильной связи":{}},"cbs":{"Оператор мобильной связи":{"lpr":0.0,"lq":0.0,"spr":0.0,"sq":0.0}},"wi":93.64,"itr":34.0,"ar":24821.25},{"ci":"422607","ri":"422611","ti":"422648","v":410365,"p":1527.2,"sc":5,"cc":4,"mdi":2.21,"pbs":{},"rbs":{"Оператор мобильной связи":{}},"cbs":{"Оператор мобильной связи":{"lpr":0.0,"lq":0.0,"spr":0.0,"sq":0.0}},"wi":128.93,"itr":20.0,"ar":28021.42},{"ci":"422607","ri":"422611","ti":"422631","v":206463,"p":2715.41,"sc":3,"cc":3,"mdi":2.16,"pbs":{},"rbs":{"Оператор мобильной связи":{}},"cbs":{"Оператор мобильной связи":{"lpr":0.0,"lq":0.0,"spr":0.0,"sq":0.0}},"wi":42.45,"itr":20.0,"ar":12180.0},{"ci":"422607","ri":"422611","ti":"422624","v":3045079,"p":235.13,"sc":8,"cc":7,"mdi":2.43,"pbs":{},"rbs":{"Оператор мобильной связи":{}},"cbs":{"Оператор мобильной связи":{"lpr":0.0,"lq":0.0,"spr":0.0,"sq":0.0}},"wi":38.49,"itr":20.0,"ar":33647.0},{"ci":"359837","ri":"359838","ti":"359845","v":623730,"p":1000.0,"sc":1,"cc":1,"mdi":3.51,"pbs":{},"rbs":{"Оператор мобильной связи":{}},"cbs":{"Оператор мобильной связи":{"lpr":0.0,"lq":0.0,"spr":0.0,"sq":0.0}},"wi":60.58,"itr":32.0,"ar":41794.2},{"ci":"359837","ri":"359838","ti":"359839","v":52564762,"p":191.68,"sc":30,"cc":23,"mdi":6.55,"pbs":{},"rbs":{"Оператор мобильной связи":{}},"cbs":{"Оператор мобильной связи":{"lpr":0.0,"lq":0.0,"spr":0.0,"sq":0.0}},"wi":164.51,"itr":32.0,"ar":54070.0},{"ci":"359837","ri":"359838","ti":"359840","v":11642822,"p":298.09,"sc":10,"cc":9,"mdi":4.82,"pbs":{},"rbs":{"Оператор мобильной связи":{}},"cbs":{"Оператор мобильной связи":{"lpr":0.0,"lq":0.0,"spr":0.0,"sq":0.0}},"wi":143.39,"itr":32.0,"ar":34732.06},{"ci":"359837","ri":"359838","ti":"359846","v":337807,"p":955.88,"sc":3,"cc":3,"mdi":1.65,"pbs":{},"rbs":{"Оператор мобильной связи":{}},"cbs":{"Оператор мобильной связи":{"lpr":0.0,"lq":0.0,"spr":0.0,"sq":0.0}},"wi":86.42,"itr":32.0,"ar":24369.68},{"ci":"359837","ri":"359838","ti":"359844","v":799026,"p":779.39,"sc":6,"cc":6,"mdi":3.99,"pbs":{},"rbs":{"Оператор мобильной связи":{}},"cbs":{"Оператор мобильной связи":{"lpr":0.0,"lq":0.0,"spr":0.0,"sq":0.0}},"wi":74.46,"itr":32.0,"ar":51235.72},{"ci":"359837","ri":"359838","ti":"359841","v":41122803,"p":68.67,"sc":9,"cc":8,"mdi":3.61,"pbs":{},"rbs":{"Оператор мобильной связи":{}},"cbs":{"Оператор мобильной связи":{"lpr":0.0,"lq":0.0,"spr":0.0,"sq":0.0}},"wi":91.16,"itr":32.0,"ar":47313.79},{"ci":"359837","ri":"359838","ti":"359842","v":5950235,"p":396.25,"sc":14,"cc":12,"mdi":5.02,"pbs":{},"rbs":{"Оператор мобильной связи":{}},"cbs":{"Оператор мобильной связи":{"lpr":0.0,"lq":0.0,"spr":0.0,"sq":0.0}},"wi":100.48,"itr":32.0,"ar":47034.75},{"ci":"359837","ri":"359838","ti":"422074","v":823478,"p":353.56,"sc":7,"cc":7,"mdi":2.92,"pbs":{},"rbs":{"Оператор мобильной связи":{}},"cbs":{"Оператор мобильной связи":{"lpr":0.0,"lq":0.0,"spr":0.0,"sq":0.0}},"wi":67.22,"itr":32.0,"ar":29562.44},{"ci":"359837","ri":"359838","ti":"359843","v":717541,"p":1409.69,"sc":7,"cc":7,"mdi":3.84,"pbs":{},"rbs":{"Оператор мобильной связи":{}},"cbs":{"Оператор мобильной связи":{"lpr":0.0,"lq":0.0,"spr":0.0,"sq":0.0}},"wi":78.18,"itr":32.0,"ar":39402.3},{"ci":"335165","ri":"335166","ti":"335168","v":549417,"p":500.0,"sc":1,"cc":1,"mdi":2.6,"pbs":{},"rbs":{"Оператор мобильной связи":{}},"cbs":{"Оператор мобильной связи":{"lpr":0.0,"lq":0.0,"spr":0.0,"sq":0.0}},"wi":37.68,"itr":35.0,"ar":17351.25},{"ci":"335165","ri":"335166","ti":"335171","v":145153,"p":800.0,"sc":1,"cc":1,"mdi":2.56,"pbs":{},"rbs":{"Оператор мобильной связи":{}},"cbs":{"Оператор мобильной связи":{"lpr":0.0,"lq":0.0,"spr":0.0,"sq":0.0}},"wi":35.04,"itr":35.0,"ar":16530.0},{"ci":"335165","ri":"335166","ti":"422021","v":5965,"p":1600.0,"sc":1,"cc":1,"mdi":0.4,"pbs":{},"rbs":{"Оператор мобильной связи":{}},"cbs":{"Оператор мобильной связи":{"lpr":0.0,"lq":0.0,"spr":0.0,"sq":0.0}},"wi":28.45,"itr":35.0,"ar":11484.31},{"ci":"335165","ri":"335166","ti":"335167","v":10466882,"p":121.05,"sc":5,"cc":5,"mdi":4.11,"pbs":{},"rbs":{"Оператор мобильной связи":{}},"cbs":{"Оператор мобильной связи":{"lpr":0.0,"lq":0.0,"spr":0.0,"sq":0.0}},"wi":42.97,"itr":35.0,"ar":27566.84},{"ci":"335165","ri":"335166","ti":"335169","v":1040441,"p":200.0,"sc":1,"cc":1,"mdi":2.91,"pbs":{},"rbs":{"Оператор мобильной связи":{}},"cbs":{"Оператор мобильной связи":{"lpr":0.0,"lq":0.0,"spr":0.0,"sq":0.0}},"wi":51.07,"itr":35.0,"ar":33128.55},{"ci":"335165","ri":"335166","ti":"335170","v":845041,"p":206.47,"sc":2,"cc":2,"mdi":2.55,"pbs":{},"rbs":{"Оператор мобильной связи":{}},"cbs":{"Оператор мобильной связи":{"lpr":0.0,"lq":0.0,"spr":0.0,"sq":0.0}},"wi":42.38,"itr":35.0,"ar":17037.41},{"ci":"423195","ri":"423196","ti":"423199","v":95805045,"p":62.02,"sc":18,"cc":14,"mdi":5.9,"pbs":{},"rbs":{"Оператор мобильной связи":{}},"cbs":{"Оператор мобильной связи":{"lpr":0.0,"lq":0.0,"spr":0.0,"sq":0.0}},"wi":60.32,"itr":27.0,"ar":20168.4},{"ci":"423195","ri":"423196","ti":"423200","v":8392021,"p":265.85,"sc":10,"cc":10,"mdi":4.26,"pbs":{},"rbs":{"Оператор мобильной связи":{}},"cbs":{"Оператор мобильной связи":{"lpr":0.0,"lq":0.0,"spr":0.0,"sq":0.0}},"wi":75.59,"itr":27.0,"ar":16883.0},{"ci":"423195","ri":"423196","ti":"423201","v":9569603,"p":176.3,"sc":4,"cc":4,"mdi":4.22,"pbs":{},"rbs":{"Оператор мобильной связи":{}},"cbs":{"Оператор мобильной связи":{"lpr":0.0,"lq":0.0,"spr":0.0,"sq":0.0}},"wi":80.59,"itr":27.0,"ar":17595.9},{"ci":"423195","ri":"423196","ti":"423207","v":815113,"p":256.4,"sc":8,"cc":6,"mdi":1.84,"pbs":{},"rbs":{"Оператор мобильной связи":{}},"cbs":{"Оператор мобильной связи":{"lpr":0.0,"lq":0.0,"spr":0.0,"sq":0.0}},"wi":38.01,"itr":27.0,"ar":10169.74},{"ci":"423195","ri":"423196","ti":"423808","v":531107,"p":53.71,"sc":5,"cc":5,"mdi":1.24,"pbs":{},"rbs":{"Оператор мобильной связи":{}},"cbs":{"Оператор мобильной связи":{"lpr":0.0,"lq":0.0,"spr":0.0,"sq":0.0}},"wi":17.85,"itr":27.0,"ar":2826.64},{"ci":"423195","ri":"423197","ti":"423206","v":236081,"p":587.59,"sc":3,"cc":3,"mdi":1.41,"pbs":{},"rbs":{"Оператор мобильной связи":{}},"cbs":{"Оператор мобильной связи":{"lpr":0.0,"lq":0.0,"spr":0.0,"sq":0.0}},"wi":33.29,"itr":29.0,"ar":8360.1},{"ci":"423195","ri":"423197","ti":"423204","v":393652,"p":1324.21,"sc":6,"cc":6,"mdi":2.25,"pbs":{},"rbs":{"Оператор мобильной связи":{}},"cbs":{"Оператор мобильной связи":{"lpr":0.0,"lq":0.0,"spr":0.0,"sq":0.0}},"wi":53.78,"itr":29.0,"ar":11082.0},{"ci":"423195","ri":"423197","ti":"423807","v":165809,"p":164.97,"sc":3,"cc":3,"mdi":1.28,"pbs":{},"rbs":{"Оператор мобильной связи":{}},"cbs":{"Оператор мобильной связи":{"lpr":0.0,"lq":0.0,"spr":0.0,"sq":0.0}},"wi":14.88,"itr":29.0,"ar":2935.96},{"ci":"423195","ri":"423197","ti":"423203","v":585000,"p":724.3,"sc":4,"cc":4,"mdi":1.77,"pbs":{},"rbs":{"Оператор мобильной связи":{}},"cbs":{"Оператор мобильной связи":{"lpr":0.0,"lq":0.0,"spr":0.0,"sq":0.0}},"wi":45.68,"itr":29.0,"ar":12870.28},{"ci":"423195","ri":"423197","ti":"423205","v":2519402,"p":86.73,"sc":7,"cc":7,"mdi":1.03,"pbs":{},"rbs":{"Оператор мобильной связи":{}},"cbs":{"Оператор мобильной связи":{"lpr":0.0,"lq":0.0,"spr":0.0,"sq":0.0}},"wi":53.31,"itr":29.0,"ar":10126.46},{"ci":"423195","ri":"423198","ti":"423202","v":7643713,"p":159.2,"sc":5,"cc":5,"mdi":3.19,"pbs":{},"rbs":{"Оператор мобильной связи":{}},"cbs":{"Оператор мобильной связи":{"lpr":0.0,"lq":0.0,"spr":0.0,"sq":0.0}},"wi":52.69,"itr":24.0,"ar":16255.37},{"ci":"423195","ri":"423198","ti":"423208","v":325964,"p":423.47,"sc":2,"cc":2,"mdi":1.76,"pbs":{},"rbs":{"Оператор мобильной связи":{}},"cbs":{"Оператор мобильной связи":{"lpr":0.0,"lq":0.0,"spr":0.0,"sq":0.0}},"wi":35.3,"itr":24.0,"ar":7384.55},{"ci":"423195","ri":"423198","ti":"423809","v":50832,"p":70.0,"sc":1,"cc":1,"mdi":0.18,"pbs":{},"rbs":{"Оператор мобильной связи":{}},"cbs":{"Оператор мобильной связи":{"lpr":0.0,"lq":0.0,"spr":0.0,"sq":0.0}},"wi":15.99,"itr":24.0,"ar":2953.93},{"ci":"423195","ri":"423198","ti":"423209","v":102274,"p":273.64,"sc":2,"cc":2,"mdi":1.07,"pbs":{},"rbs":{"Оператор мобильной связи":{}},"cbs":{"Оператор мобильной связи":{"lpr":0.0,"lq":0.0,"spr":0.0,"sq":0.0}},"wi":16.81,"itr":24.0,"ar":4200.22},{"ci":"15734","ri":"15735","ti":"16322","v":25088,"p":380.0,"sc":1,"cc":1,"mdi":0.14,"pbs":{},"rbs":{"Оператор мобильной связи":{}},"cbs":{"Оператор мобильной связи":{"lpr":0.0,"lq":0.0,"spr":0.0,"sq":0.0}},"wi":14.37,"itr":30.0,"ar":5599.0},{"ci":"15734","ri":"15735","ti":"15737","v":6768852,"p":107.83,"sc":6,"cc":6,"mdi":2.87,"pbs":{},"rbs":{"Оператор мобильной связи":{}},"cbs":{"Оператор мобильной связи":{"lpr":0.0,"lq":0.0,"spr":0.0,"sq":0.0}},"wi":50.35,"itr":30.0,"ar":6935.0},{"ci":"15734","ri":"15735","ti":"422521","v":282996,"p":230.03,"sc":2,"cc":2,"mdi":2.26,"pbs":{},"rbs":{"Оператор мобильной связи":{}},"cbs":{"Оператор мобильной связи":{"lpr":0.0,"lq":0.0,"spr":0.0,"sq":0.0}},"wi":65.16,"itr":30.0,"ar":9100.48},{"ci":"15734","ri":"15735","ti":"15741","v":2407403,"p":252.9,"sc":4,"cc":4,"mdi":2.89,"pbs":{},"rbs":{"Оператор мобильной связи":{}},"cbs":{"Оператор мобильной связи":{"lpr":0.0,"lq":0.0,"spr":0.0,"sq":0.0}},"wi":52.72,"itr":30.0,"ar":12642.0},{"ci":"15734","ri":"15735","ti":"15738","v":18882169,"p":65.19,"sc":6,"cc":6,"mdi":3.45,"pbs":{},"rbs":{"Оператор мобильной связи":{}},"cbs":{"Оператор мобильной связи":{"lpr":0.0,"lq":0.0,"spr":0.0,"sq":0.0}},"wi":77.06,"itr":30.0,"ar":8971.65},{"ci":"15734","ri":"15735","ti":"15739","v":3995535,"p":49.85,"sc":2,"cc":2,"mdi":1.05,"pbs":{},"rbs":{"Оператор мобильной связи":{}},"cbs":{"Оператор мобильной связи":{"lpr":0.0,"lq":0.0,"spr":0.0,"sq":0.0}},"wi":48.69,"itr":30.0,"ar":9661.0},{"ci":"15734","ri":"15735","ti":"15736","v":112760147,"p":93.87,"sc":27,"cc":27,"mdi":4.74,"pbs":{},"rbs":{"Оператор мобильной связи":{}},"cbs":{"Оператор мобильной связи":{"lpr":0.0,"lq":0.0,"spr":0.0,"sq":0.0}},"wi":60.17,"itr":30.0,"ar":29818.0},{"ci":"15734","ri":"15735","ti":"15740","v":2851083,"p":250.39,"sc":3,"cc":3,"mdi":3.02,"pbs":{},"rbs":{"Оператор мобильной связи":{}},"cbs":{"Оператор мобильной связи":{"lpr":0.0,"lq":0.0,"spr":0.0,"sq":0.0}},"wi":52.3,"itr":30.0,"ar":7122.0},{"ci":"15734","ri":"15735","ti":"302148","v":851970,"p":40.0,"sc":1,"cc":1,"mdi":1.4,"pbs":{},"rbs":{"Оператор мобильной связи":{}},"cbs":{"Оператор мобильной связи":{"lpr":0.0,"lq":0.0,"spr":0.0,"sq":0.0}},"wi":31.13,"itr":30.0,"ar":2668.71},{"ci":"2931","ri":"2961","ti":"366263","v":949614,"p":139.84,"sc":5,"cc":5,"mdi":1.46,"pbs":{},"rbs":{"Оператор мобильной связи":{}},"cbs":{"Оператор мобильной связи":{"lpr":0.0,"lq":0.0,"spr":0.0,"sq":0.0}},"wi":10.82,"itr":4.0,"ar":32048.1},{"ci":"2931","ri":"2961","ti":"2964","v":2980759,"p":37.53,"sc":13,"cc":13,"mdi":1.22,"pbs":{},"rbs":{"Оператор мобильной связи":{}},"cbs":{"Оператор мобильной связи":{"lpr":0.0,"lq":0.0,"spr":0.0,"sq":0.0}},"wi":9.47,"itr":4.0,"ar":3634.54},{"ci":"2931","ri":"2961","ti":"422543","v":612021,"p":203.03,"sc":7,"cc":7,"mdi":2.26,"pbs":{},"rbs":{"Оператор мобильной связи":{}},"cbs":{"Оператор мобильной связи":{"lpr":0.0,"lq":0.0,"spr":0.0,"sq":0.0}},"wi":28.89,"itr":4.0,"ar":18051.48},{"ci":"2931","ri":"2961","ti":"2962","v":3536195,"p":135.9,"sc":12,"cc":12,"mdi":1.99,"pbs":{},"rbs":{"Оператор мобильной связи":{}},"cbs":{"Оператор мобильной связи":{"lpr":0.0,"lq":0.0,"spr":0.0,"sq":0.0}},"wi":25.78,"itr":4.0,"ar":45486.95},{"ci":"2931","ri":"2961","ti":"2963","v":249959,"p":176.79,"sc":8,"cc":8,"mdi":0.99,"pbs":{},"rbs":{"Оператор мобильной связи":{}},"cbs":{"Оператор мобильной связи":{"lpr":0.0,"lq":0.0,"spr":0.0,"sq":0.0}},"wi":13.62,"itr":4.0,"ar":7692.42},{"ci":"2931","ri":"2939","ti":"422530","v":140539,"p":246.54,"sc":3,"cc":3,"mdi":1.95,"pbs":{},"rbs":{"Оператор мобильной связи":{}},"cbs":{"Оператор мобильной связи":{"lpr":0.0,"lq":0.0,"spr":0.0,"sq":0.0}},"wi":23.31,"itr":24.0,"ar":4516.0},{"ci":"2931","ri":"2939","ti":"2943","v":4752477,"p":192.82,"sc":17,"cc":16,"mdi":2.04,"pbs":{},"rbs":{"Оператор мобильной связи":{}},"cbs":{"Оператор мобильной связи":{"lpr":0.0,"lq":0.0,"spr":0.0,"sq":0.0}},"wi":30.42,"itr":24.0,"ar":33269.04},{"ci":"2931","ri":"2939","ti":"2940","v":12205111,"p":228.97,"sc":16,"cc":15,"mdi":3.38,"pbs":{},"rbs":{"Оператор мобильной связи":{}},"cbs":{"Оператор мобильной связи":{"lpr":0.0,"lq":0.0,"spr":0.0,"sq":0.0}},"wi":48.55,"itr":24.0,"ar":16417.8},{"ci":"2931","ri":"2939","ti":"2944","v":1173719,"p":82.6,"sc":6,"cc":6,"mdi":0.85,"pbs":{},"rbs":{"Оператор мобильной связи":{}},"cbs":{"Оператор мобильной связи":{"lpr":0.0,"lq":0.0,"spr":0.0,"sq":0.0}},"wi":10.64,"itr":24.0,"ar":2764.0},{"ci":"2931","ri":"2939","ti":"2941","v":1507793,"p":77.87,"sc":8,"cc":8,"mdi":0.82,"pbs":{},"rbs":{"Оператор мобильной связи":{}},"cbs":{"Оператор мобильной связи":{"lpr":0.0,"lq":0.0,"spr":0.0,"sq":0.0}},"wi":14.14,"itr":24.0,"ar":6272.75},{"ci":"2931","ri":"2939","ti":"423572","v":1680913,"p":234.54,"sc":6,"cc":6,"mdi":2.1,"pbs":{},"rbs":{"Оператор мобильной связи":{}},"cbs":{"Оператор мобильной связи":{"lpr":0.0,"lq":0.0,"spr":0.0,"sq":0.0}},"wi":31.09,"itr":24.0,"ar":4447.13},{"ci":"2931","ri":"2939","ti":"2942","v":4485553,"p":216.02,"sc":11,"cc":11,"mdi":2.11,"pbs":{},"rbs":{"Оператор мобильной связи":{}},"cbs":{"Оператор мобильной связи":{"lpr":0.0,"lq":0.0,"spr":0.0,"sq":0.0}},"wi":21.66,"itr":24.0,"ar":25994.85},{"ci":"2931","ri":"331858","ti":"423533","v":169606,"p":79.49,"sc":4,"cc":4,"mdi":1.33,"pbs":{},"rbs":{"Оператор мобильной связи":{}},"cbs":{"Оператор мобильной связи":{"lpr":0.0,"lq":0.0,"spr":0.0,"sq":0.0}},"wi":17.91,"itr":25.0,"ar":2954.91},{"ci":"2931","ri":"331858","ti":"331860","v":8404244,"p":81.62,"sc":5,"cc":5,"mdi":2.14,"pbs":{},"rbs":{"Оператор мобильной связи":{}},"cbs":{"Оператор мобильной связи":{"lpr":0.0,"lq":0.0,"spr":0.0,"sq":0.0}},"wi":43.02,"itr":25.0,"ar":6979.0},{"ci":"2931","ri":"331858","ti":"331870","v":6657661,"p":72.49,"sc":11,"cc":11,"mdi":1.47,"pbs":{},"rbs":{"Оператор мобильной связи":{}},"cbs":{"Оператор мобильной связи":{"lpr":0.0,"lq":0.0,"spr":0.0,"sq":0.0}},"wi":6.42,"itr":25.0,"ar":1092.68},{"ci":"2931","ri":"331858","ti":"331866","v":951657,"p":126.87,"sc":9,"cc":9,"mdi":1.27,"pbs":{},"rbs":{"Оператор мобильной связи":{}},"cbs":{"Оператор мобильной связи":{"lpr":0.0,"lq":0.0,"spr":0.0,"sq":0.0}},"wi":27.06,"itr":25.0,"ar":4384.14},{"ci":"2931","ri":"331858","ti":"331864","v":2489347,"p":88.0,"sc":5,"cc":5,"mdi":2.31,"pbs":{},"rbs":{"Оператор мобильной связи":{}},"cbs":{"Оператор мобильной связи":{"lpr":0.0,"lq":0.0,"spr":0.0,"sq":0.0}},"wi":35.89,"itr":25.0,"ar":4401.0},{"ci":"2931","ri":"331858","ti":"331872","v":301987,"p":84.75,"sc":5,"cc":5,"mdi":1.84,"pbs":{},"rbs":{"Оператор мобильной связи":{}},"cbs":{"Оператор мобильной связи":{"lpr":0.0,"lq":0.0,"spr":0.0,"sq":0.0}},"wi":14.29,"itr":25.0,"ar":2309.59},{"ci":"2931","ri":"331858","ti":"331873","v":1255970,"p":79.47,"sc":2,"cc":2,"mdi":2.82,"pbs":{},"rbs":{"Оператор мобильной связи":{}},"cbs":{"Оператор мобильной связи":{"lpr":0.0,"lq":0.0,"spr":0.0,"sq":0.0}},"wi":17.75,"itr":25.0,"ar":2902.65},{"ci":"2931","ri":"331858","ti":"331871","v":2677813,"p":82.03,"sc":3,"cc":3,"mdi":3.38,"pbs":{},"rbs":{"Оператор мобильной связи":{}},"cbs":{"Оператор мобильной связи":{"lpr":0.0,"lq":0.0,"spr":0.0,"sq":0.0}},"wi":53.55,"itr":25.0,"ar":6911.37},{"ci":"2931","ri":"331858","ti":"331859","v":9385599,"p":189.92,"sc":11,"cc":11,"mdi":3.15,"pbs":{},"rbs":{"Оператор мобильной связи":{}},"cbs":{"Оператор мобильной связи":{"lpr":0.0,"lq":0.0,"spr":0.0,"sq":0.0}},"wi":71.42,"itr":25.0,"ar":20106.79},{"ci":"2931","ri":"331858","ti":"331862","v":3882946,"p":99.27,"sc":9,"cc":9,"mdi":2.45,"pbs":{},"rbs":{"Оператор мобильной связи":{}},"cbs":{"Оператор мобильной связи":{"lpr":0.0,"lq":0.0,"spr":0.0,"sq":0.0}},"wi":37.5,"itr":25.0,"ar":10421.0},{"ci":"2931","ri":"331858","ti":"331863","v":2795618,"p":81.03,"sc":4,"cc":4,"mdi":2.41,"pbs":{},"rbs":{"Оператор мобильной связи":{}},"cbs":{"Оператор мобильной связи":{"lpr":0.0,"lq":0.0,"spr":0.0,"sq":0.0}},"wi":29.71,"itr":25.0,"ar":3468.7},{"ci":"2931","ri":"331858","ti":"331867","v":3962643,"p":88.38,"sc":3,"cc":3,"mdi":2.63,"pbs":{},"rbs":{"Оператор мобильной связи":{}},"cbs":{"Оператор мобильной связи":{"lpr":0.0,"lq":0.0,"spr":0.0,"sq":0.0}},"wi":43.39,"itr":25.0,"ar":6550.75},{"ci":"2931","ri":"331858","ti":"2934","v":107952206,"p":126.37,"sc":58,"cc":53,"mdi":3.34,"pbs":{},"rbs":{"Оператор мобильной связи":{}},"cbs":{"Оператор мобильной связи":{"lpr":0.0,"lq":0.0,"spr":0.0,"sq":0.0}},"wi":60.74,"itr":25.0,"ar":23899.27},{"ci":"2931","ri":"331858","ti":"331868","v":493886,"p":103.78,"sc":8,"cc":8,"mdi":1.72,"pbs":{},"rbs":{"Оператор мобильной связи":{}},"cbs":{"Оператор мобильной связи":{"lpr":0.0,"lq":0.0,"spr":0.0,"sq":0.0}},"wi":12.38,"itr":25.0,"ar":1365.65},{"ci":"2931","ri":"331858","ti":"331865","v":2565454,"p":80.97,"sc":4,"cc":4,"mdi":2.32,"pbs":{},"rbs":{"Оператор мобильной связи":{}},"cbs":{"Оператор мобильной связи":{"lpr":0.0,"lq":0.0,"spr":0.0,"sq":0.0}},"wi":32.85,"itr":25.0,"ar":3445.83},{"ci":"2931","ri":"331858","ti":"331869","v":362453,"p":79.54,"sc":3,"cc":3,"mdi":1.73,"pbs":{},"rbs":{"Оператор мобильной связи":{}},"cbs":{"Оператор мобильной связи":{"lpr":0.0,"lq":0.0,"spr":0.0,"sq":0.0}},"wi":9.02,"itr":25.0,"ar":2927.63},{"ci":"2931","ri":"331858","ti":"331861","v":5075605,"p":99.53,"sc":10,"cc":10,"mdi":1.98,"pbs":{},"rbs":{"Оператор мобильной связи":{}},"cbs":{"Оператор мобильной связи":{"lpr":0.0,"lq":0.0,"spr":0.0,"sq":0.0}},"wi":14.08,"itr":25.0,"ar":5489.35},{"ci":"2931","ri":"2956","ti":"371340","v":1171386,"p":407.86,"sc":5,"cc":5,"mdi":1.29,"pbs":{},"rbs":{"Оператор мобильной связи":{}},"cbs":{"Оператор мобильной связи":{"lpr":0.0,"lq":0.0,"spr":0.0,"sq":0.0}},"wi":46.24,"itr":30.0,"ar":14956.2},{"ci":"2931","ri":"2956","ti":"2960","v":80808,"p":98.46,"sc":2,"cc":2,"mdi":0.17,"pbs":{},"rbs":{"Оператор мобильной связи":{}},"cbs":{"Оператор мобильной связи":{"lpr":0.0,"lq":0.0,"spr":0.0,"sq":0.0}},"wi":13.53,"itr":30.0,"ar":4905.15},{"ci":"2931","ri":"2956","ti":"2959","v":1190179,"p":410.73,"sc":12,"cc":11,"mdi":1.41,"pbs":{},"rbs":{"Оператор мобильной связи":{}},"cbs":{"Оператор мобильной связи":{"lpr":0.0,"lq":0.0,"spr":0.0,"sq":0.0}},"wi":34.67,"itr":30.0,"ar":6829.2},{"ci":"2931","ri":"2956","ti":"2957","v":4598110,"p":464.81,"sc":18,"cc":11,"mdi":2.21,"pbs":{},"rbs":{"Оператор мобильной связи":{}},"cbs":{"Оператор мобильной связи":{"lpr":0.0,"lq":0.0,"spr":0.0,"sq":0.0}},"wi":41.76,"itr":30.0,"ar":11355.75},{"ci":"2931","ri":"2956","ti":"367967","v":153621,"p":203.57,"sc":4,"cc":2,"mdi":1.58,"pbs":{},"rbs":{"Оператор мобильной связи":{}},"cbs":{"Оператор мобильной связи":{"lpr":0.0,"lq":0.0,"spr":0.0,"sq":0.0}},"wi":9.83,"itr":30.0,"ar":3128.9},{"ci":"2931","ri":"2956","ti":"2958","v":826151,"p":410.91,"sc":6,"cc":5,"mdi":1.01,"pbs":{},"rbs":{"Оператор мобильной связи":{}},"cbs":{"Оператор мобильной связи":{"lpr":0.0,"lq":0.0,"spr":0.0,"sq":0.0}},"wi":28.04,"itr":30.0,"ar":8695.05},{"ci":"2931","ri":"2956","ti":"10716","v":503062,"p":403.36,"sc":6,"cc":6,"mdi":1.43,"pbs":{},"rbs":{"Оператор мобильной связи":{}},"cbs":{"Оператор мобильной связи":{"lpr":0.0,"lq":0.0,"spr":0.0,"sq":0.0}},"wi":23.05,"itr":30.0,"ar":5838.39},{"ci":"2931","ri":"2950","ti":"2951","v":15660400,"p":46.68,"sc":14,"cc":12,"mdi":1.22,"pbs":{},"rbs":{"Оператор мобильной связи":{}},"cbs":{"Оператор мобильной связи":{"lpr":0.0,"lq":0.0,"spr":0.0,"sq":0.0}},"wi":31.11,"itr":22.0,"ar":8987.57},{"ci":"2931","ri":"2950","ti":"422086","v":619969,"p":323.04,"sc":6,"cc":6,"mdi":1.63,"pbs":{},"rbs":{"Оператор мобильной связи":{}},"cbs":{"Оператор мобильной связи":{"lpr":0.0,"lq":0.0,"spr":0.0,"sq":0.0}},"wi":30.76,"itr":22.0,"ar":6189.8},{"ci":"2931","ri":"2950","ti":"2954","v":319859,"p":256.96,"sc":6,"cc":6,"mdi":1.32,"pbs":{},"rbs":{"Оператор мобильной связи":{}},"cbs":{"Оператор мобильной связи":{"lpr":0.0,"lq":0.0,"spr":0.0,"sq":0.0}},"wi":14.59,"itr":22.0,"ar":2142.54},{"ci":"2931","ri":"2950","ti":"2955","v":126940,"p":371.23,"sc":4,"cc":4,"mdi":1.43,"pbs":{},"rbs":{"Оператор мобильной связи":{}},"cbs":{"Оператор мобильной связи":{"lpr":0.0,"lq":0.0,"spr":0.0,"sq":0.0}},"wi":14.0,"itr":22.0,"ar":2764.65},{"ci":"2931","ri":"2950","ti":"2953","v":389468,"p":215.95,"sc":7,"cc":6,"mdi":1.41,"pbs":{},"rbs":{"Оператор мобильной связи":{}},"cbs":{"Оператор мобильной связи":{"lpr":0.0,"lq":0.0,"spr":0.0,"sq":0.0}},"wi":13.35,"itr":22.0,"ar":2549.0},{"ci":"2931","ri":"2950","ti":"2952","v":1103871,"p":102.75,"sc":12,"cc":10,"mdi":0.89,"pbs":{},"rbs":{"Оператор мобильной связи":{}},"cbs":{"Оператор мобильной связи":{"lpr":0.0,"lq":0.0,"spr":0.0,"sq":0.0}},"wi":12.06,"itr":22.0,"ar":4685.78},{"ci":"2931","ri":"2932","ti":"2935","v":4543287,"p":20.2,"sc":7,"cc":7,"mdi":1.39,"pbs":{},"rbs":{"Оператор мобильной связи":{}},"cbs":{"Оператор мобильной связи":{"lpr":0.0,"lq":0.0,"spr":0.0,"sq":0.0}},"wi":11.29,"itr":30.0,"ar":2959.11},{"ci":"2931","ri":"2932","ti":"366651","v":152458,"p":32.65,"sc":2,"cc":2,"mdi":0.85,"pbs":{},"rbs":{"Оператор мобильной связи":{}},"cbs":{"Оператор мобильной связи":{"lpr":0.0,"lq":0.0,"spr":0.0,"sq":0.0}},"wi":10.85,"itr":30.0,"ar":2609.62},{"ci":"2931","ri":"2932","ti":"2938","v":81740,"p":200.0,"sc":1,"cc":1,"mdi":0.46,"pbs":{},"rbs":{"Оператор мобильной связи":{}},"cbs":{"Оператор мобильной связи":{"lpr":0.0,"lq":0.0,"spr":0.0,"sq":0.0}},"wi":8.77,"itr":30.0,"ar":2201.85},{"ci":"2931","ri":"2932","ti":"422085","v":44457,"p":112.98,"sc":2,"cc":2,"mdi":0.65,"pbs":{},"rbs":{"Оператор мобильной связи":{}},"cbs":{"Оператор мобильной связи":{"lpr":0.0,"lq":0.0,"spr":0.0,"sq":0.0}},"wi":7.1,"itr":30.0,"ar":1734.16},{"ci":"2931","ri":"2932","ti":"367968","v":5642924,"p":106.12,"sc":5,"cc":5,"mdi":3.14,"pbs":{},"rbs":{"Оператор мобильной связи":{}},"cbs":{"Оператор мобильной связи":{"lpr":0.0,"lq":0.0,"spr":0.0,"sq":0.0}},"wi":49.83,"itr":30.0,"ar":12461.82},{"ci":"2931","ri":"2932","ti":"423527","v":887092,"p":253.95,"sc":6,"cc":6,"mdi":2.54,"pbs":{},"rbs":{"Оператор мобильной связи":{}},"cbs":{"Оператор мобильной связи":{"lpr":0.0,"lq":0.0,"spr":0.0,"sq":0.0}},"wi":25.85,"itr":30.0,"ar":3351.6},{"ci":"2931","ri":"2932","ti":"2937","v":1378771,"p":55.8,"sc":5,"cc":5,"mdi":0.38,"pbs":{},"rbs":{"Оператор мобильной связи":{}},"cbs":{"Оператор мобильной связи":{"lpr":0.0,"lq":0.0,"spr":0.0,"sq":0.0}},"wi":23.37,"itr":30.0,"ar":12770.0},{"ci":"2931","ri":"2932","ti":"371339","v":2022678,"p":45.79,"sc":5,"cc":5,"mdi":1.56,"pbs":{},"rbs":{"Оператор мобильной связи":{}},"cbs":{"Оператор мобильной связи":{"lpr":0.0,"lq":0.0,"spr":0.0,"sq":0.0}},"wi":27.58,"itr":30.0,"ar":22860.03},{"ci":"2931","ri":"2932","ti":"2933","v":219892263,"p":48.24,"sc":71,"cc":55,"mdi":2.52,"pbs":{},"rbs":{"Оператор мобильной связи":{}},"cbs":{"Оператор мобильной связи":{"lpr":0.0,"lq":0.0,"spr":0.0,"sq":0.0}},"wi":33.37,"itr":30.0,"ar":8902.0},{"ci":"2931","ri":"2932","ti":"423509","v":252177,"p":5.74,"sc":5,"cc":5,"mdi":0.96,"pbs":{},"rbs":{"Оператор мобильной связи":{}},"cbs":{"Оператор мобильной связи":{"lpr":0.0,"lq":0.0,"spr":0.0,"sq":0.0}},"wi":10.54,"itr":30.0,"ar":1896.98},{"ci":"2931","ri":"2932","ti":"422040","v":1467604,"p":142.17,"sc":4,"cc":4,"mdi":1.76,"pbs":{},"rbs":{"Оператор мобильной связи":{}},"cbs":{"Оператор мобильной связи":{"lpr":0.0,"lq":0.0,"spr":0.0,"sq":0.0}},"wi":37.01,"itr":30.0,"ar":4470.75},{"ci":"2931","ri":"2932","ti":"2936","v":12629520,"p":16.91,"sc":7,"cc":7,"mdi":1.4,"pbs":{},"rbs":{"Оператор мобильной связи":{}},"cbs":{"Оператор мобильной связи":{"lpr":0.0,"lq":0.0,"spr":0.0,"sq":0.0}},"wi":11.61,"itr":30.0,"ar":5577.6},{"ci":"2931","ri":"2945","ti":"423510","v":20122,"p":216.62,"sc":2,"cc":2,"mdi":0.41,"pbs":{},"rbs":{"Оператор мобильной связи":{}},"cbs":{"Оператор мобильной связи":{"lpr":0.0,"lq":0.0,"spr":0.0,"sq":0.0}},"wi":15.11,"itr":55.0,"ar":11636.89},{"ci":"2931","ri":"2945","ti":"423564","v":1329179,"p":15.96,"sc":4,"cc":4,"mdi":0.77,"pbs":{},"rbs":{"Оператор мобильной связи":{}},"cbs":{"Оператор мобильной связи":{"lpr":0.0,"lq":0.0,"spr":0.0,"sq":0.0}},"wi":9.31,"itr":55.0,"ar":12410.84},{"ci":"2931","ri":"2945","ti":"366652","v":42209,"p":35.0,"sc":1,"cc":1,"mdi":0.4,"pbs":{},"rbs":{"Оператор мобильной связи":{}},"cbs":{"Оператор мобильной связи":{"lpr":0.0,"lq":0.0,"spr":0.0,"sq":0.0}},"wi":7.38,"itr":55.0,"ar":3822.42},{"ci":"2931","ri":"2945","ti":"2947","v":142942,"p":109.52,"sc":4,"cc":4,"mdi":0.34,"pbs":{},"rbs":{"Оператор мобильной связи":{}},"cbs":{"Оператор мобильной связи":{"lpr":0.0,"lq":0.0,"spr":0.0,"sq":0.0}},"wi":7.97,"itr":55.0,"ar":8775.76},{"ci":"2931","ri":"2945","ti":"352279","v":27121,"p":80.0,"sc":1,"cc":1,"mdi":0.3,"pbs":{},"rbs":{"Оператор мобильной связи":{}},"cbs":{"Оператор мобильной связи":{"lpr":0.0,"lq":0.0,"spr":0.0,"sq":0.0}},"wi":8.37,"itr":55.0,"ar":7510.68},{"ci":"2931","ri":"2945","ti":"2948","v":4305309,"p":7.36,"sc":12,"cc":11,"mdi":0.54,"pbs":{},"rbs":{"Оператор мобильной связи":{}},"cbs":{"Оператор мобильной связи":{"lpr":0.0,"lq":0.0,"spr":0.0,"sq":0.0}},"wi":3.13,"itr":55.0,"ar":8835.0},{"ci":"2931","ri":"2945","ti":"423566","v":59006,"p":15.0,"sc":1,"cc":1,"mdi":0.26,"pbs":{},"rbs":{"Оператор мобильной связи":{}},"cbs":{"Оператор мобильной связи":{"lpr":0.0,"lq":0.0,"spr":0.0,"sq":0.0}},"wi":3.53,"itr":55.0,"ar":2538.38},{"ci":"2931","ri":"2945","ti":"422506","v":8512,"p":240.21,"sc":2,"cc":2,"mdi":0.18,"pbs":{},"rbs":{"Оператор мобильной связи":{}},"cbs":{"Оператор мобильной связи":{"lpr":0.0,"lq":0.0,"spr":0.0,"sq":0.0}},"wi":8.67,"itr":55.0,"ar":5389.88},{"ci":"2931","ri":"2945","ti":"2949","v":32981,"p":91.99,"sc":2,"cc":2,"mdi":0.19,"pbs":{},"rbs":{"Оператор мобильной связи":{}},"cbs":{"Оператор мобильной связи":{"lpr":0.0,"lq":0.0,"spr":0.0,"sq":0.0}},"wi":8.74,"itr":55.0,"ar":12459.89},{"ci":"2931","ri":"2945","ti":"2946","v":985077,"p":43.41,"sc":5,"cc":5,"mdi":1.21,"pbs":{},"rbs":{"Оператор мобильной связи":{}},"cbs":{"Оператор мобильной связи":{"lpr":0.0,"lq":0.0,"spr":0.0,"sq":0.0}},"wi":7.69,"itr":55.0,"ar":11810.39},{"ci":"2931","ri":"2945","ti":"5033","v":207282,"p":104.74,"sc":5,"cc":5,"mdi":0.73,"pbs":{},"rbs":{"Оператор мобильной связи":{}},"cbs":{"Оператор мобильной связи":{"lpr":0.0,"lq":0.0,"spr":0.0,"sq":0.0}},"wi":9.17,"itr":55.0,"ar":23075.85},{"ci":"2931","ri":"2945","ti":"423001","v":70636,"p":109.9,"sc":4,"cc":4,"mdi":0.55,"pbs":{},"rbs":{"Оператор мобильной связи":{}},"cbs":{"Оператор мобильной связи":{"lpr":0.0,"lq":0.0,"spr":0.0,"sq":0.0}},"wi":10.89,"itr":55.0,"ar":8952.77},{"ci":"2931","ri":"2945","ti":"423568","v":12537,"p":329.58,"sc":3,"cc":3,"mdi":0.21,"pbs":{},"rbs":{"Оператор мобильной связи":{}},"cbs":{"Оператор мобильной связи":{"lpr":0.0,"lq":0.0,"spr":0.0,"sq":0.0}},"wi":11.56,"itr":55.0,"ar":1346.63},{"ci":"423084","ri":"423085","ti":"423086","v":209677,"p":87.9,"sc":4,"cc":4,"mdi":5.82,"pbs":{},"rbs":{"Оператор мобильной связи":{}},"cbs":{"Оператор мобильной связи":{"lpr":0.0,"lq":0.0,"spr":0.0,"sq":0.0}},"wi":44.58,"itr":50.0,"ar":217095.49},{"ci":"310392","ri":"310393","ti":"423031","v":233849,"p":78.09,"sc":3,"cc":3,"mdi":1.54,"pbs":{},"rbs":{"Оператор мобильной связи":{}},"cbs":{"Оператор мобильной связи":{"lpr":0.0,"lq":0.0,"spr":0.0,"sq":0.0}},"wi":14.87,"itr":5.0,"ar":1462.97},{"ci":"310392","ri":"310393","ti":"423508","v":129356,"p":242.61,"sc":2,"cc":2,"mdi":1.46,"pbs":{},"rbs":{"Оператор мобильной связи":{}},"cbs":{"Оператор мобильной связи":{"lpr":0.0,"lq":0.0,"spr":0.0,"sq":0.0}},"wi":18.88,"itr":5.0,"ar":1248.0},{"ci":"310392","ri":"310393","ti":"310397","v":728776,"p":81.68,"sc":3,"cc":3,"mdi":0.89,"pbs":{},"rbs":{"Оператор мобильной связи":{}},"cbs":{"Оператор мобильной связи":{"lpr":0.0,"lq":0.0,"spr":0.0,"sq":0.0}},"wi":16.33,"itr":5.0,"ar":2341.0},{"ci":"310392","ri":"310393","ti":"310399","v":1685539,"p":116.87,"sc":3,"cc":3,"mdi":1.69,"pbs":{},"rbs":{"Оператор мобильной связи":{}},"cbs":{"Оператор мобильной связи":{"lpr":0.0,"lq":0.0,"spr":0.0,"sq":0.0}},"wi":9.71,"itr":5.0,"ar":4360.27},{"ci":"310392","ri":"310393","ti":"423019","v":189003,"p":111.83,"sc":2,"cc":2,"mdi":1.23,"pbs":{},"rbs":{"Оператор мобильной связи":{}},"cbs":{"Оператор мобильной связи":{"lpr":0.0,"lq":0.0,"spr":0.0,"sq":0.0}},"wi":17.61,"itr":5.0,"ar":2541.18},{"ci":"310392","ri":"310393","ti":"423032","v":210746,"p":122.43,"sc":2,"cc":2,"mdi":1.18,"pbs":{},"rbs":{"Оператор мобильной связи":{}},"cbs":{"Оператор мобильной связи":{"lpr":0.0,"lq":0.0,"spr":0.0,"sq":0.0}},"wi":16.51,"itr":5.0,"ar":1358.6},{"ci":"310392","ri":"310393","ti":"422512","v":352523,"p":127.66,"sc":4,"cc":4,"mdi":1.33,"pbs":{},"rbs":{"Оператор мобильной связи":{}},"cbs":{"Оператор мобильной связи":{"lpr":0.0,"lq":0.0,"spr":0.0,"sq":0.0}},"wi":13.05,"itr":5.0,"ar":2483.2},{"ci":"310392","ri":"310393","ti":"423020","v":201929,"p":106.75,"sc":2,"cc":2,"mdi":1.1,"pbs":{},"rbs":{"Оператор мобильной связи":{}},"cbs":{"Оператор мобильной связи":{"lpr":0.0,"lq":0.0,"spr":0.0,"sq":0.0}},"wi":17.19,"itr":5.0,"ar":2619.25},{"ci":"310392","ri":"310393","ti":"310395","v":4407982,"p":66.74,"sc":7,"cc":7,"mdi":1.64,"pbs":{},"rbs":{"Оператор мобильной связи":{}},"cbs":{"Оператор мобильной связи":{"lpr":0.0,"lq":0.0,"spr":0.0,"sq":0.0}},"wi":33.2,"itr":5.0,"ar":13485.0},{"ci":"310392","ri":"310393","ti":"310400","v":6011522,"p":88.23,"sc":11,"cc":10,"mdi":1.45,"pbs":{},"rbs":{"Оператор мобильной связи":{}},"cbs":{"Оператор мобильной связи":{"lpr":0.0,"lq":0.0,"spr":0.0,"sq":0.0}},"wi":7.21,"itr":5.0,"ar":1546.0},{"ci":"310392","ri":"310393","ti":"310396","v":628699,"p":983.28,"sc":7,"cc":7,"mdi":2.94,"pbs":{},"rbs":{"Оператор мобильной связи":{}},"cbs":{"Оператор мобильной связи":{"lpr":0.0,"lq":0.0,"spr":0.0,"sq":0.0}},"wi":43.27,"itr":5.0,"ar":13225.0},{"ci":"310392","ri":"310393","ti":"310394","v":39571502,"p":221.16,"sc":25,"cc":25,"mdi":4.76,"pbs":{},"rbs":{"Оператор мобильной связи":{}},"cbs":{"Оператор мобильной связи":{"lpr":0.0,"lq":0.0,"spr":0.0,"sq":0.0}},"wi":61.93,"itr":5.0,"ar":16960.0},{"ci":"310392","ri":"310393","ti":"423567","v":49881,"p":388.26,"sc":3,"cc":3,"mdi":1.1,"pbs":{},"rbs":{"Оператор мобильной связи":{}},"cbs":{"Оператор мобильной связи":{"lpr":0.0,"lq":0.0,"spr":0.0,"sq":0.0}},"wi":16.78,"itr":5.0,"ar":1480.0},{"ci":"310392","ri":"310393","ti":"423030","v":82216,"p":201.49,"sc":2,"cc":2,"mdi":1.07,"pbs":{},"rbs":{"Оператор мобильной связи":{}},"cbs":{"Оператор мобильной связи":{"lpr":0.0,"lq":0.0,"spr":0.0,"sq":0.0}},"wi":16.36,"itr":5.0,"ar":1578.66},{"ci":"310392","ri":"310393","ti":"310398","v":3575990,"p":108.15,"sc":3,"cc":3,"mdi":2.68,"pbs":{},"rbs":{"Оператор мобильной связи":{}},"cbs":{"Оператор мобильной связи":{"lpr":0.0,"lq":0.0,"spr":0.0,"sq":0.0}},"wi":50.57,"itr":5.0,"ar":16352.18},{"ci":"310392","ri":"310393","ti":"423029","v":233177,"p":380.8,"sc":3,"cc":3,"mdi":2.26,"pbs":{},"rbs":{"Оператор мобильной связи":{}},"cbs":{"Оператор мобильной связи":{"lpr":0.0,"lq":0.0,"spr":0.0,"sq":0.0}},"wi":28.67,"itr":5.0,"ar":3018.65},{"ci":"310392","ri":"310393","ti":"423576","v":92621,"p":111.0,"sc":1,"cc":1,"mdi":1.15,"pbs":{},"rbs":{"Оператор мобильной связи":{}},"cbs":{"Оператор мобильной связи":{"lpr":0.0,"lq":0.0,"spr":0.0,"sq":0.0}},"wi":14.6,"itr":5.0,"ar":1972.0},{"ci":"3010","ri":"3011","ti":"422996","v":2243751,"p":78.68,"sc":4,"cc":4,"mdi":2.18,"pbs":{},"rbs":{"Оператор мобильной связи":{}},"cbs":{"Оператор мобильной связи":{"lpr":0.0,"lq":0.0,"spr":0.0,"sq":0.0}},"wi":38.92,"itr":32.0,"ar":6791.0},{"ci":"3010","ri":"3011","ti":"3014","v":14802734,"p":59.67,"sc":9,"cc":9,"mdi":2.56,"pbs":{},"rbs":{"Оператор мобильной связи":{}},"cbs":{"Оператор мобильной связи":{"lpr":0.0,"lq":0.0,"spr":0.0,"sq":0.0}},"wi":30.3,"itr":32.0,"ar":4897.0},{"ci":"3010","ri":"3011","ti":"3015","v":13398835,"p":115.67,"sc":8,"cc":8,"mdi":2.86,"pbs":{},"rbs":{"Оператор мобильной связи":{}},"cbs":{"Оператор мобильной связи":{"lpr":0.0,"lq":0.0,"spr":0.0,"sq":0.0}},"wi":41.97,"itr":32.0,"ar":8028.0},{"ci":"3010","ri":"3011","ti":"3016","v":2470050,"p":168.67,"sc":7,"cc":7,"mdi":1.62,"pbs":{},"rbs":{"Оператор мобильной связи":{}},"cbs":{"Оператор мобильной связи":{"lpr":0.0,"lq":0.0,"spr":0.0,"sq":0.0}},"wi":24.23,"itr":32.0,"ar":5155.5},{"ci":"3010","ri":"3011","ti":"3012","v":72829297,"p":92.42,"sc":29,"cc":28,"mdi":3.39,"pbs":{},"rbs":{"Оператор мобильной связи":{}},"cbs":{"Оператор мобильной связи":{"lpr":0.0,"lq":0.0,"spr":0.0,"sq":0.0}},"wi":57.42,"itr":32.0,"ar":14041.0},{"ci":"3010","ri":"3011","ti":"3017","v":1803120,"p":23.29,"sc":6,"cc":6,"mdi":0.97,"pbs":{},"rbs":{"Оператор мобильной связи":{}},"cbs":{"Оператор мобильной связи":{"lpr":0.0,"lq":0.0,"spr":0.0,"sq":0.0}},"wi":7.36,"itr":32.0,"ar":1781.0},{"ci":"3010","ri":"3011","ti":"422998","v":90496,"p":98.0,"sc":2,"cc":2,"mdi":0.58,"pbs":{},"rbs":{"Оператор мобильной связи":{}},"cbs":{"Оператор мобильной связи":{"lpr":0.0,"lq":0.0,"spr":0.0,"sq":0.0}},"wi":17.89,"itr":32.0,"ar":2934.0},{"ci":"3010","ri":"3011","ti":"13055","v":3351419,"p":218.33,"sc":4,"cc":4,"mdi":4.38,"pbs":{},"rbs":{"Оператор мобильной связи":{}},"cbs":{"Оператор мобильной связи":{"lpr":0.0,"lq":0.0,"spr":0.0,"sq":0.0}},"wi":50.37,"itr":32.0,"ar":8579.25},{"ci":"3010","ri":"3011","ti":"3013","v":24741500,"p":54.03,"sc":16,"cc":16,"mdi":2.71,"pbs":{},"rbs":{"Оператор мобильной связи":{}},"cbs":{"Оператор мобильной связи":{"lpr":0.0,"lq":0.0,"spr":0.0,"sq":0.0}},"wi":28.96,"itr":32.0,"ar":9094.3},{"ci":"3010","ri":"3018","ti":"3022","v":2383791,"p":29.94,"sc":6,"cc":6,"mdi":1.16,"pbs":{},"rbs":{"Оператор мобильной связи":{}},"cbs":{"Оператор мобильной связи":{"lpr":0.0,"lq":0.0,"spr":0.0,"sq":0.0}},"wi":11.03,"itr":31.0,"ar":3230.82},{"ci":"3010","ri":"3018","ti":"3021","v":1457924,"p":65.84,"sc":7,"cc":6,"mdi":1.48,"pbs":{},"rbs":{"Оператор мобильной связи":{}},"cbs":{"Оператор мобильной связи":{"lpr":0.0,"lq":0.0,"spr":0.0,"sq":0.0}},"wi":16.91,"itr":31.0,"ar":2014.95},{"ci":"3010","ri":"3018","ti":"3020","v":952422,"p":64.75,"sc":2,"cc":2,"mdi":1.39,"pbs":{},"rbs":{"Оператор мобильной связи":{}},"cbs":{"Оператор мобильной связи":{"lpr":0.0,"lq":0.0,"spr":0.0,"sq":0.0}},"wi":17.12,"itr":31.0,"ar":1753.5},{"ci":"3010","ri":"3018","ti":"3019","v":11538981,"p":68.29,"sc":5,"cc":5,"mdi":2.35,"pbs":{},"rbs":{"Оператор мобильной связи":{}},"cbs":{"Оператор мобильной связи":{"lpr":0.0,"lq":0.0,"spr":0.0,"sq":0.0}},"wi":31.02,"itr":31.0,"ar":8084.64},{"ci":"3010","ri":"3018","ti":"423550","v":68703,"p":92.56,"sc":3,"cc":3,"mdi":0.47,"pbs":{},"rbs":{"Оператор мобильной связи":{}},"cbs":{"Оператор мобильной связи":{"lpr":0.0,"lq":0.0,"spr":0.0,"sq":0.0}},"wi":16.79,"itr":31.0,"ar":2248.69},{"ci":"3010","ri":"3018","ti":"423532","v":818497,"p":67.55,"sc":5,"cc":5,"mdi":1.53,"pbs":{},"rbs":{"Оператор мобильной связи":{}},"cbs":{"Оператор мобильной связи":{"lpr":0.0,"lq":0.0,"spr":0.0,"sq":0.0}},"wi":24.88,"itr":31.0,"ar":1862.0},{"ci":"3010","ri":"3023","ti":"3025","v":1851758,"p":49.12,"sc":5,"cc":5,"mdi":0.47,"pbs":{},"rbs":{"Оператор мобильной связи":{}},"cbs":{"Оператор мобильной связи":{"lpr":0.0,"lq":0.0,"spr":0.0,"sq":0.0}},"wi":29.1,"itr":27.0,"ar":14717.85},{"ci":"3010","ri":"3023","ti":"3024","v":29555928,"p":66.55,"sc":12,"cc":12,"mdi":3.04,"pbs":{},"rbs":{"Оператор мобильной связи":{}},"cbs":{"Оператор мобильной связи":{"lpr":0.0,"lq":0.0,"spr":0.0,"sq":0.0}},"wi":47.55,"itr":27.0,"ar":48807.15},{"ci":"3010","ri":"3023","ti":"3028","v":3260470,"p":11.95,"sc":3,"cc":3,"mdi":0.72,"pbs":{},"rbs":{"Оператор мобильной связи":{}},"cbs":{"Оператор мобильной связи":{"lpr":0.0,"lq":0.0,"spr":0.0,"sq":0.0}},"wi":12.76,"itr":27.0,"ar":4593.02},{"ci":"3010","ri":"3023","ti":"3026","v":2651542,"p":33.55,"sc":4,"cc":4,"mdi":0.77,"pbs":{},"rbs":{"Оператор мобильной связи":{}},"cbs":{"Оператор мобильной связи":{"lpr":0.0,"lq":0.0,"spr":0.0,"sq":0.0}},"wi":28.41,"itr":27.0,"ar":18103.05},{"ci":"3010","ri":"3023","ti":"3027","v":1596164,"p":23.44,"sc":6,"cc":6,"mdi":1.38,"pbs":{},"rbs":{"Оператор мобильной связи":{}},"cbs":{"Оператор мобильной связи":{"lpr":0.0,"lq":0.0,"spr":0.0,"sq":0.0}},"wi":10.97,"itr":27.0,"ar":1852.2},{"ci":"3010","ri":"3023","ti":"422089","v":1867940,"p":34.87,"sc":5,"cc":5,"mdi":2.18,"pbs":{},"rbs":{"Оператор мобильной связи":{}},"cbs":{"Оператор мобильной связи":{"lpr":0.0,"lq":0.0,"spr":0.0,"sq":0.0}},"wi":43.53,"itr":27.0,"ar":7168.0},{"ci":"301309","ri":"301310","ti":"422978","v":933595,"p":294.56,"sc":2,"cc":2,"mdi":2.22,"pbs":{},"rbs":{"Оператор мобильной связи":{}},"cbs":{"Оператор мобильной связи":{"lpr":0.0,"lq":0.0,"spr":0.0,"sq":0.0}},"wi":72.41,"itr":36.0,"ar":18524.34},{"ci":"301309","ri":"301310","ti":"422038","v":669637,"p":343.63,"sc":4,"cc":4,"mdi":1.68,"pbs":{},"rbs":{"Оператор мобильной связи":{}},"cbs":{"Оператор мобильной связи":{"lpr":0.0,"lq":0.0,"spr":0.0,"sq":0.0}},"wi":65.41,"itr":36.0,"ar":16419.26},{"ci":"301309","ri":"301310","ti":"301315","v":317876,"p":398.59,"sc":3,"cc":3,"mdi":2.55,"pbs":{},"rbs":{"Оператор мобильной связи":{}},"cbs":{"Оператор мобильной связи":{"lpr":0.0,"lq":0.0,"spr":0.0,"sq":0.0}},"wi":52.0,"itr":36.0,"ar":24191.06},{"ci":"301309","ri":"301310","ti":"301313","v":879489,"p":448.32,"sc":5,"cc":5,"mdi":1.39,"pbs":{},"rbs":{"Оператор мобильной связи":{}},"cbs":{"Оператор мобильной связи":{"lpr":0.0,"lq":0.0,"spr":0.0,"sq":0.0}},"wi":78.65,"itr":36.0,"ar":23809.55},{"ci":"301309","ri":"301310","ti":"301314","v":0,"p":0.0,"sc":0,"cc":0,"mdi":0.0,"pbs":{},"rbs":{"Оператор мобильной связи":{}},"cbs":{"Оператор мобильной связи":{"lpr":0.0,"lq":0.0,"spr":0.0,"sq":0.0}},"wi":80.52,"itr":36.0,"ar":24424.79},{"ci":"301309","ri":"301310","ti":"301311","v":21592341,"p":168.47,"sc":22,"cc":20,"mdi":3.8,"pbs":{},"rbs":{"Оператор мобильной связи":{}},"cbs":{"Оператор мобильной связи":{"lpr":0.0,"lq":0.0,"spr":0.0,"sq":0.0}},"wi":79.27,"itr":36.0,"ar":38363.75},{"ci":"301309","ri":"301310","ti":"301312","v":1943599,"p":436.52,"sc":6,"cc":5,"mdi":2.74,"pbs":{},"rbs":{"Оператор мобильной связи":{}},"cbs":{"Оператор мобильной связи":{"lpr":0.0,"lq":0.0,"spr":0.0,"sq":0.0}},"wi":79.2,"itr":36.0,"ar":33306.07},{"ci":"15906","ri":"3030","ti":"3037","v":2602156,"p":325.1,"sc":3,"cc":3,"mdi":3.29,"pbs":{},"rbs":{"Оператор мобильной связи":{}},"cbs":{"Оператор мобильной связи":{"lpr":0.0,"lq":0.0,"spr":0.0,"sq":0.0}},"wi":68.54,"itr":18.0,"ar":70070.0},{"ci":"15906","ri":"3030","ti":"3039","v":1247134,"p":344.6,"sc":4,"cc":4,"mdi":3.09,"pbs":{},"rbs":{"Оператор мобильной связи":{}},"cbs":{"Оператор мобильной связи":{"lpr":0.0,"lq":0.0,"spr":0.0,"sq":0.0}},"wi":55.45,"itr":18.0,"ar":90355.95},{"ci":"15906","ri":"3030","ti":"422528","v":443373,"p":463.04,"sc":3,"cc":3,"mdi":2.98,"pbs":{},"rbs":{"Оператор мобильной связи":{}},"cbs":{"Оператор мобильной связи":{"lpr":0.0,"lq":0.0,"spr":0.0,"sq":0.0}},"wi":77.91,"itr":18.0,"ar":114203.99},{"ci":"15906","ri":"3030","ti":"3033","v":1098677,"p":950.02,"sc":7,"cc":7,"mdi":3.35,"pbs":{},"rbs":{"Оператор мобильной связи":{}},"cbs":{"Оператор мобильной связи":{"lpr":0.0,"lq":0.0,"spr":0.0,"sq":0.0}},"wi":87.23,"itr":18.0,"ar":24038.0},{"ci":"15906","ri":"3030","ti":"3032","v":9314267,"p":356.32,"sc":8,"cc":8,"mdi":4.35,"pbs":{},"rbs":{"Оператор мобильной связи":{}},"cbs":{"Оператор мобильной связи":{"lpr":0.0,"lq":0.0,"spr":0.0,"sq":0.0}},"wi":60.82,"itr":18.0,"ar":31207.64},{"ci":"15906","ri":"3030","ti":"3041","v":415335,"p":781.01,"sc":2,"cc":2,"mdi":2.35,"pbs":{},"rbs":{"Оператор мобильной связи":{}},"cbs":{"Оператор мобильной связи":{"lpr":0.0,"lq":0.0,"spr":0.0,"sq":0.0}},"wi":54.35,"itr":18.0,"ar":28095.9},{"ci":"15906","ri":"3030","ti":"3035","v":907561,"p":783.79,"sc":4,"cc":4,"mdi":3.33,"pbs":{},"rbs":{"Оператор мобильной связи":{}},"cbs":{"Оператор мобильной связи":{"lpr":0.0,"lq":0.0,"spr":0.0,"sq":0.0}},"wi":45.35,"itr":18.0,"ar":24771.53},{"ci":"15906","ri":"3030","ti":"3031","v":69675535,"p":130.89,"sc":37,"cc":34,"mdi":4.85,"pbs":{},"rbs":{"Оператор мобильной связи":{}},"cbs":{"Оператор мобильной связи":{"lpr":0.0,"lq":0.0,"spr":0.0,"sq":0.0}},"wi":64.5,"itr":18.0,"ar":80283.0},{"ci":"15906","ri":"3030","ti":"3040","v":7224800,"p":25.17,"sc":6,"cc":5,"mdi":1.97,"pbs":{},"rbs":{"Оператор мобильной связи":{}},"cbs":{"Оператор мобильной связи":{"lpr":0.0,"lq":0.0,"spr":0.0,"sq":0.0}},"wi":49.49,"itr":18.0,"ar":31340.6},{"ci":"15906","ri":"3030","ti":"3038","v":78909,"p":364.42,"sc":2,"cc":2,"mdi":0.28,"pbs":{},"rbs":{"Оператор мобильной связи":{}},"cbs":{"Оператор мобильной связи":{"lpr":0.0,"lq":0.0,"spr":0.0,"sq":0.0}},"wi":71.78,"itr":18.0,"ar":26499.0},{"ci":"15906","ri":"3030","ti":"423573","v":14223,"p":500.0,"sc":1,"cc":1,"mdi":1.58,"pbs":{},"rbs":{"Оператор мобильной связи":{}},"cbs":{"Оператор мобильной связи":{"lpr":0.0,"lq":0.0,"spr":0.0,"sq":0.0}},"wi":45.32,"itr":18.0,"ar":21386.0},{"ci":"15906","ri":"3030","ti":"3036","v":1278073,"p":751.08,"sc":5,"cc":5,"mdi":3.75,"pbs":{},"rbs":{"Оператор мобильной связи":{}},"cbs":{"Оператор мобильной связи":{"lpr":0.0,"lq":0.0,"spr":0.0,"sq":0.0}},"wi":62.57,"itr":18.0,"ar":129511.61},{"ci":"15906","ri":"3030","ti":"422018","v":109926,"p":190.83,"sc":2,"cc":2,"mdi":0.92,"pbs":{},"rbs":{"Оператор мобильной связи":{}},"cbs":{"Оператор мобильной связи":{"lpr":0.0,"lq":0.0,"spr":0.0,"sq":0.0}},"wi":51.48,"itr":18.0,"ar":51121.97},{"ci":"15906","ri":"3030","ti":"3034","v":2164138,"p":361.19,"sc":4,"cc":4,"mdi":3.31,"pbs":{},"rbs":{"Оператор мобильной связи":{}},"cbs":{"Оператор мобильной связи":{"lpr":0.0,"lq":0.0,"spr":0.0,"sq":0.0}},"wi":53.0,"itr":18.0,"ar":26236.06},{"ci":"423103","ri":"423105","ti":"423113","v":87682,"p":896.25,"sc":2,"cc":2,"mdi":2.08,"pbs":{},"rbs":{"Оператор мобильной связи":{}},"cbs":{"Оператор мобильной связи":{"lpr":0.0,"lq":0.0,"spr":0.0,"sq":0.0}},"wi":30.55,"itr":19.0,"ar":12666.15},{"ci":"423103","ri":"423105","ti":"423114","v":73983,"p":450.0,"sc":2,"cc":2,"mdi":1.13,"pbs":{},"rbs":{"Оператор мобильной связи":{}},"cbs":{"Оператор мобильной связи":{"lpr":0.0,"lq":0.0,"spr":0.0,"sq":0.0}},"wi":33.42,"itr":19.0,"ar":7530.3},{"ci":"423103","ri":"423105","ti":"423112","v":249158,"p":327.21,"sc":3,"cc":3,"mdi":2.25,"pbs":{},"rbs":{"Оператор мобильной связи":{}},"cbs":{"Оператор мобильной связи":{"lpr":0.0,"lq":0.0,"spr":0.0,"sq":0.0}},"wi":28.29,"itr":19.0,"ar":7140.0},{"ci":"423103","ri":"423105","ti":"423111","v":87153,"p":1234.35,"sc":2,"cc":2,"mdi":1.69,"pbs":{},"rbs":{"Оператор мобильной связи":{}},"cbs":{"Оператор мобильной связи":{"lpr":0.0,"lq":0.0,"spr":0.0,"sq":0.0}},"wi":34.77,"itr":19.0,"ar":16887.0},{"ci":"423103","ri":"423104","ti":"423108","v":429410,"p":886.83,"sc":4,"cc":4,"mdi":3.34,"pbs":{},"rbs":{"Оператор мобильной связи":{}},"cbs":{"Оператор мобильной связи":{"lpr":0.0,"lq":0.0,"spr":0.0,"sq":0.0}},"wi":54.01,"itr":19.0,"ar":12677.28},{"ci":"423103","ri":"423104","ti":"423107","v":15957927,"p":68.29,"sc":5,"cc":5,"mdi":3.75,"pbs":{},"rbs":{"Оператор мобильной связи":{}},"cbs":{"Оператор мобильной связи":{"lpr":0.0,"lq":0.0,"spr":0.0,"sq":0.0}},"wi":50.17,"itr":19.0,"ar":13784.9},{"ci":"423103","ri":"423104","ti":"423109","v":348152,"p":729.34,"sc":4,"cc":4,"mdi":2.13,"pbs":{},"rbs":{"Оператор мобильной связи":{}},"cbs":{"Оператор мобильной связи":{"lpr":0.0,"lq":0.0,"spr":0.0,"sq":0.0}},"wi":85.11,"itr":19.0,"ar":13397.58},{"ci":"423103","ri":"423104","ti":"423110","v":223487,"p":504.25,"sc":5,"cc":5,"mdi":2.47,"pbs":{},"rbs":{"Оператор мобильной связи":{}},"cbs":{"Оператор мобильной связи":{"lpr":0.0,"lq":0.0,"spr":0.0,"sq":0.0}},"wi":42.04,"itr":19.0,"ar":9408.0},{"ci":"423103","ri":"423104","ti":"423106","v":132193,"p":911.07,"sc":2,"cc":2,"mdi":2.59,"pbs":{},"rbs":{"Оператор мобильной связи":{}},"cbs":{"Оператор мобильной связи":{"lpr":0.0,"lq":0.0,"spr":0.0,"sq":0.0}},"wi":43.07,"itr":19.0,"ar":9600.0},{"ci":"325655","ri":"325656","ti":"423548","v":27238,"p":325.18,"sc":2,"cc":2,"mdi":1.44,"pbs":{},"rbs":{"Оператор мобильной связи":{}},"cbs":{"Оператор мобильной связи":{"lpr":0.0,"lq":0.0,"spr":0.0,"sq":0.0}},"wi":22.5,"itr":24.0,"ar":6938.0},{"ci":"325655","ri":"325656","ti":"325659","v":44617,"p":503.0,"sc":1,"cc":1,"mdi":0.73,"pbs":{},"rbs":{"Оператор мобильной связи":{}},"cbs":{"Оператор мобильной связи":{"lpr":0.0,"lq":0.0,"spr":0.0,"sq":0.0}},"wi":29.61,"itr":24.0,"ar":18327.0},{"ci":"325655","ri":"325656","ti":"422019","v":30175,"p":300.0,"sc":1,"cc":1,"mdi":0.69,"pbs":{},"rbs":{"Оператор мобильной связи":{}},"cbs":{"Оператор мобильной связи":{"lpr":0.0,"lq":0.0,"spr":0.0,"sq":0.0}},"wi":29.25,"itr":24.0,"ar":10395.0},{"ci":"325655","ri":"325656","ti":"325657","v":5830674,"p":43.94,"sc":3,"cc":3,"mdi":2.12,"pbs":{},"rbs":{"Оператор мобильной связи":{}},"cbs":{"Оператор мобильной связи":{"lpr":0.0,"lq":0.0,"spr":0.0,"sq":0.0}},"wi":34.3,"itr":24.0,"ar":38695.0},{"ci":"325655","ri":"325656","ti":"325658","v":71897,"p":250.0,"sc":1,"cc":1,"mdi":0.67,"pbs":{},"rbs":{"Оператор мобильной связи":{}},"cbs":{"Оператор мобильной связи":{"lpr":0.0,"lq":0.0,"spr":0.0,"sq":0.0}},"wi":22.05,"itr":24.0,"ar":22685.0}]