[{"cn":"Infotech2003","pi":"3867","ui":"3995142","t":2896377,"r":2896376,"q":21.24,"p":39000.0,"mot":"L","mo":9000.0},{"cn":"xErcegua Trade","pi":"3867","ui":"4625003","t":132327,"r":132327,"q":9.44,"p":9000.0,"mot":"U","mo":0.0},{"cn":"Atac Co.","pi":"3867","ui":"3953939","t":24835,"r":24835,"q":2.86,"p":12500.0,"mot":"U","mo":0.0},{"cn":"Kaya Corp","pi":"3867","ui":"4574767","t":734,"r":54,"q":8.26,"p":8000.0,"mot":"U","mo":0.0},{"cn":"RoMa Inc.","pi":"3867","ui":"3988424","t":60352,"r":60152,"q":17.6,"p":12000.0,"mot":"U","mo":0.0},{"cn":"LC Technology Group","pi":"3867","ui":"4304806","t":61378,"r":61128,"q":5.86,"p":10500.0,"mot":"U","mo":0.0},{"cn":"xErcegua Trade","pi":"3867","ui":"4686728","t":876196,"r":865586,"q":21.84,"p":15000.0,"mot":"U","mo":0.0},{"cn":"Vinhas","pi":"3867","ui":"4099561","t":635240,"r":635240,"q":11.43,"p":30000.0,"mot":"L","mo":2000.0},{"cn":"xErcegua Trade","pi":"3867","ui":"4607074","t":15599,"r":15599,"q":8.48,"p":10000.0,"mot":"U","mo":0.0},{"cn":"Quadriad Box","pi":"3867","ui":"4696690","t":458931,"r":458931,"q":14.52,"p":10000.0,"mot":"U","mo":0.0},{"cn":"fernando911 Trade","pi":"3867","ui":"2898837","t":201,"r":96,"q":1.0,"p":1639.9,"mot":"L","mo":40.0},{"cn":"LUSIBERIA","pi":"3867","ui":"4696761","t":6953,"r":6953,"q":4.31,"p":8000.0,"mot":"U","mo":0.0},{"cn":"Egg-Roll International","pi":"3867","ui":"4541495","t":260082,"r":260082,"q":25.07,"p":30000.0,"mot":"U","mo":0.0},{"cn":"Egg-Roll International","pi":"3867","ui":"4541464","t":7320,"r":7320,"q":9.25,"p":13000.0,"mot":"U","mo":0.0}]