[{"cn":"Morituri te salutant INC","pi":"359855","ui":"4091759","t":213,"r":213,"q":8.24,"p":110000.0,"mot":"L","mo":10.0},{"cn":"Mitsofos Corporation","pi":"359855","ui":"3270841","t":1476,"r":1476,"q":40.46,"p":320000.0,"mot":"U","mo":0.0},{"cn":"Infotech2003","pi":"359855","ui":"3111061","t":20919,"r":20919,"q":14.9,"p":300000.0,"mot":"U","mo":0.0},{"cn":"phoenix ltd","pi":"359855","ui":"4498396","t":72,"r":72,"q":15.06,"p":140000.0,"mot":"U","mo":0.0},{"cn":"Vinhas","pi":"359855","ui":"4019919","t":11993,"r":11993,"q":10.96,"p":300000.0,"mot":"U","mo":0.0},{"cn":"Oaklye Group","pi":"359855","ui":"4114396","t":5,"r":5,"q":25.8,"p":185000.0,"mot":"U","mo":0.0},{"cn":"Mitsofos Corporation","pi":"359855","ui":"3881593","t":14478,"r":14478,"q":46.58,"p":490000.0,"mot":"U","mo":0.0},{"cn":"Pantela Inc","pi":"359855","ui":"4451527","t":257,"r":257,"q":12.47,"p":120000.0,"mot":"U","mo":0.0},{"cn":"rui.filipe.75 International","pi":"359855","ui":"4618492","t":3390,"r":3390,"q":20.7,"p":150000.0,"mot":"U","mo":0.0},{"cn":"Mitsofos Corporation","pi":"359855","ui":"2603903","t":31835,"r":31835,"q":46.57,"p":415000.0,"mot":"U","mo":0.0},{"cn":"gfife11 Industries","pi":"359855","ui":"3696019","t":61,"r":61,"q":37.42,"p":270000.0,"mot":"U","mo":0.0},{"cn":"ydaf International","pi":"359855","ui":"3202468","t":40424,"r":40424,"q":27.49,"p":211107.68,"mot":"U","mo":0.0},{"cn":"ITG Corp.","pi":"359855","ui":"4539809","t":15,"r":15,"q":16.53,"p":77777.0,"mot":"U","mo":0.0}]